{
  "category": {
    "id": 192,
    "title": "Docker образы (images)",
    "description": " ",
    "parentId": 164
  },
  "totalQuestions": 12,
  "downloadedAt": "2026-03-10T10:06:46.577Z",
  "questions": [
    {
      "current": {
        "id": 1855,
        "type": "boolean",
        "text": "{\"type\":\"doc\",\"content\":[{\"type\":\"paragraph\",\"attrs\":{\"textAlign\":null},\"content\":[{\"type\":\"text\",\"text\":\"Что такое Docker образ?\"}]}]}",
        "title": "Что такое Docker образ?",
        "order": 500100,
        "premium": false,
        "isPopular": false,
        "explanation": "{\"type\":\"doc\",\"content\":[{\"type\":\"paragraph\",\"attrs\":{\"textAlign\":null},\"content\":[{\"type\":\"text\",\"text\":\"Docker-образ — это неизменяемый (immutable) шаблон файловой системы, из которого Docker запускает контейнер. В образе находится всё, что нужно приложению для работы: зависимости, системные библиотеки, конфигурация, бинарники, переменные окружения и инструкции для запуска.\"}]},{\"type\":\"horizontalRule\"},{\"type\":\"heading\",\"attrs\":{\"textAlign\":null,\"level\":3},\"content\":[{\"type\":\"text\",\"marks\":[{\"type\":\"bold\"}],\"text\":\"Ключевые свойства Docker-образа\"}]},{\"type\":\"orderedList\",\"attrs\":{\"start\":1,\"type\":null},\"content\":[{\"type\":\"listItem\",\"content\":[{\"type\":\"paragraph\",\"attrs\":{\"textAlign\":null},\"content\":[{\"type\":\"text\",\"marks\":[{\"type\":\"bold\"}],\"text\":\"Immutable\"},{\"type\":\"text\",\"text\":\" — образ нельзя изменить после сборки; любые изменения происходят путём создания нового слоя.\"}]}]},{\"type\":\"listItem\",\"content\":[{\"type\":\"paragraph\",\"attrs\":{\"textAlign\":null},\"content\":[{\"type\":\"text\",\"marks\":[{\"type\":\"bold\"}],\"text\":\"Layered structure\"},{\"type\":\"text\",\"text\":\" — образ состоит из слоёв (каждая инструкция \"},{\"type\":\"text\",\"marks\":[{\"type\":\"code\"}],\"text\":\"Dockerfile\"},{\"type\":\"text\",\"text\":\" создаёт новый слой). Это экономит место и ускоряет сборку.\"}]}]},{\"type\":\"listItem\",\"content\":[{\"type\":\"paragraph\",\"attrs\":{\"textAlign\":null},\"content\":[{\"type\":\"text\",\"marks\":[{\"type\":\"bold\"}],\"text\":\"Reusable\"},{\"type\":\"text\",\"text\":\" — один образ можно использовать для запуска множества контейнеров.\"}]}]},{\"type\":\"listItem\",\"content\":[{\"type\":\"paragraph\",\"attrs\":{\"textAlign\":null},\"content\":[{\"type\":\"text\",\"marks\":[{\"type\":\"bold\"}],\"text\":\"Portable\"},{\"type\":\"text\",\"text\":\" — образ можно перенести и запустить на любой машине, где есть Docker.\"}]}]}]},{\"type\":\"horizontalRule\"},{\"type\":\"heading\",\"attrs\":{\"textAlign\":null,\"level\":3},\"content\":[{\"type\":\"text\",\"marks\":[{\"type\":\"bold\"}],\"text\":\"Связь с контейнером\"}]},{\"type\":\"bulletList\",\"content\":[{\"type\":\"listItem\",\"content\":[{\"type\":\"paragraph\",\"attrs\":{\"textAlign\":null},\"content\":[{\"type\":\"text\",\"marks\":[{\"type\":\"bold\"}],\"text\":\"Image = шаблон\"},{\"type\":\"text\",\"text\":\" (как ISO-образ или слепок)\"}]}]},{\"type\":\"listItem\",\"content\":[{\"type\":\"paragraph\",\"attrs\":{\"textAlign\":null},\"content\":[{\"type\":\"text\",\"marks\":[{\"type\":\"bold\"}],\"text\":\"Container = запущенный экземпляр image’а\"}]}]}]},{\"type\":\"horizontalRule\"},{\"type\":\"heading\",\"attrs\":{\"textAlign\":null,\"level\":3},\"content\":[{\"type\":\"text\",\"marks\":[{\"type\":\"bold\"}],\"text\":\"Где хранятся образы\"}]},{\"type\":\"bulletList\",\"content\":[{\"type\":\"listItem\",\"content\":[{\"type\":\"paragraph\",\"attrs\":{\"textAlign\":null},\"content\":[{\"type\":\"text\",\"text\":\"локально на машине;\"}]}]},{\"type\":\"listItem\",\"content\":[{\"type\":\"paragraph\",\"attrs\":{\"textAlign\":null},\"content\":[{\"type\":\"text\",\"text\":\"в registry (например, Docker Hub, GitLab registry, ECR и т.п.).\"}]}]}]},{\"type\":\"horizontalRule\"},{\"type\":\"paragraph\",\"attrs\":{\"textAlign\":null},\"content\":[{\"type\":\"text\",\"marks\":[{\"type\":\"bold\"}],\"text\":\"В одной фразе:\"},{\"type\":\"text\",\"text\":\" Docker-образ — это многоразовый слойный шаблон, позволяющий воспроизводимо запускать приложение в контейнере.\"}]}]}",
        "grade": "trainee",
        "language": null,
        "generationSource": "USER",
        "framework": null,
        "expectedAnswer": null,
        "categoryId": 192,
        "createdAt": "2025-10-22T08:01:06.784Z",
        "updatedAt": "2025-10-22T08:01:06.784Z",
        "favoriteByUsers": [],
        "userProgress": [],
        "category": {
          "id": 192,
          "title": "Docker образы (images)",
          "directions": [
            {
              "categoryId": 192,
              "directionId": 5,
              "direction": {
                "id": 5,
                "title": "Инструменты и технологии",
                "order": 5,
                "isReady": true,
                "isVisible": true,
                "languages": [],
                "hasGrades": null,
                "frameworks": [],
                "createdAt": "2025-09-07T10:01:35.439Z",
                "updatedAt": "2025-11-26T11:09:24.423Z"
              }
            }
          ],
          "parent": {
            "title": "Docker",
            "id": 164,
            "parent": null
          }
        }
      },
      "previous": {
        "title": "Как Docker обеспечивает изоляцию процессов?",
        "id": 1854,
        "premium": false,
        "category": {
          "id": 191,
          "parent": {
            "title": "Docker",
            "id": 164,
            "parent": null
          },
          "directions": [
            {
              "directionId": 5
            }
          ]
        }
      },
      "next": {
        "title": "Чем Docker образ отличается от контейнера?",
        "id": 1856,
        "premium": false,
        "category": {
          "id": 192,
          "parent": {
            "title": "Docker",
            "id": 164,
            "parent": null
          },
          "directions": [
            {
              "directionId": 5
            }
          ]
        }
      }
    },
    {
      "current": {
        "id": 1856,
        "type": "boolean",
        "text": "{\"type\":\"doc\",\"content\":[{\"type\":\"paragraph\",\"attrs\":{\"textAlign\":null},\"content\":[{\"type\":\"text\",\"text\":\"Чем Docker образ отличается от контейнера?\"}]}]}",
        "title": "Чем Docker образ отличается от контейнера?",
        "order": 500101,
        "premium": false,
        "isPopular": false,
        "explanation": "{\"type\":\"doc\",\"content\":[{\"type\":\"paragraph\",\"attrs\":{\"textAlign\":null},\"content\":[{\"type\":\"text\",\"text\":\"Разница в том, что \"},{\"type\":\"text\",\"marks\":[{\"type\":\"bold\"}],\"text\":\"образ — это шаблон\"},{\"type\":\"text\",\"text\":\", а \"},{\"type\":\"text\",\"marks\":[{\"type\":\"bold\"}],\"text\":\"контейнер — это запущенный экземпляр этого шаблона.\"}]},{\"type\":\"horizontalRule\"},{\"type\":\"heading\",\"attrs\":{\"textAlign\":null,\"level\":3},\"content\":[{\"type\":\"text\",\"marks\":[{\"type\":\"bold\"}],\"text\":\"Docker образ (image)\"}]},{\"type\":\"bulletList\",\"content\":[{\"type\":\"listItem\",\"content\":[{\"type\":\"paragraph\",\"attrs\":{\"textAlign\":null},\"content\":[{\"type\":\"text\",\"text\":\"Статичен, неизменяем\"}]}]},{\"type\":\"listItem\",\"content\":[{\"type\":\"paragraph\",\"attrs\":{\"textAlign\":null},\"content\":[{\"type\":\"text\",\"text\":\"Содержит набор слоёв файловой системы и конфигурацию\"}]}]},{\"type\":\"listItem\",\"content\":[{\"type\":\"paragraph\",\"attrs\":{\"textAlign\":null},\"content\":[{\"type\":\"text\",\"text\":\"Нужен только как \"},{\"type\":\"text\",\"marks\":[{\"type\":\"bold\"}],\"text\":\"шаблон для запуска контейнеров\"}]}]},{\"type\":\"listItem\",\"content\":[{\"type\":\"paragraph\",\"attrs\":{\"textAlign\":null},\"content\":[{\"type\":\"text\",\"text\":\"Аналог: \"},{\"type\":\"text\",\"marks\":[{\"type\":\"italic\"}],\"text\":\"установочный ISO или «слепок» системы\"}]}]}]},{\"type\":\"horizontalRule\"},{\"type\":\"heading\",\"attrs\":{\"textAlign\":null,\"level\":3},\"content\":[{\"type\":\"text\",\"marks\":[{\"type\":\"bold\"}],\"text\":\"Docker контейнер (container)\"}]},{\"type\":\"bulletList\",\"content\":[{\"type\":\"listItem\",\"content\":[{\"type\":\"paragraph\",\"attrs\":{\"textAlign\":null},\"content\":[{\"type\":\"text\",\"text\":\"Динамичен, изменяем при работе\"}]}]},{\"type\":\"listItem\",\"content\":[{\"type\":\"paragraph\",\"attrs\":{\"textAlign\":null},\"content\":[{\"type\":\"text\",\"text\":\"Это \"},{\"type\":\"text\",\"marks\":[{\"type\":\"bold\"}],\"text\":\"процесс\"},{\"type\":\"text\",\"text\":\", запущенный на основе образа, в изолированной среде\"}]}]},{\"type\":\"listItem\",\"content\":[{\"type\":\"paragraph\",\"attrs\":{\"textAlign\":null},\"content\":[{\"type\":\"text\",\"text\":\"Имеет собственную файловую систему, сетевую изоляцию, PID namespace и т.п.\"}]}]},{\"type\":\"listItem\",\"content\":[{\"type\":\"paragraph\",\"attrs\":{\"textAlign\":null},\"content\":[{\"type\":\"text\",\"text\":\"Живёт, пока работает процесс внутри\"}]}]},{\"type\":\"listItem\",\"content\":[{\"type\":\"paragraph\",\"attrs\":{\"textAlign\":null},\"content\":[{\"type\":\"text\",\"text\":\"Аналог: \"},{\"type\":\"text\",\"marks\":[{\"type\":\"italic\"}],\"text\":\"реально запущенная ОС с ISO-образа\"}]}]}]},{\"type\":\"horizontalRule\"},{\"type\":\"heading\",\"attrs\":{\"textAlign\":null,\"level\":3},\"content\":[{\"type\":\"text\",\"marks\":[{\"type\":\"bold\"}],\"text\":\"Главное различие в одной строке\"}]},{\"type\":\"table\",\"content\":[{\"type\":\"tableRow\",\"content\":[{\"type\":\"tableHeader\",\"attrs\":{\"colspan\":1,\"rowspan\":1,\"colwidth\":null},\"content\":[{\"type\":\"paragraph\",\"attrs\":{\"textAlign\":null},\"content\":[{\"type\":\"text\",\"text\":\"Образ\"}]}]},{\"type\":\"tableHeader\",\"attrs\":{\"colspan\":1,\"rowspan\":1,\"colwidth\":null},\"content\":[{\"type\":\"paragraph\",\"attrs\":{\"textAlign\":null},\"content\":[{\"type\":\"text\",\"text\":\"Контейнер\"}]}]}]},{\"type\":\"tableRow\",\"content\":[{\"type\":\"tableCell\",\"attrs\":{\"colspan\":1,\"rowspan\":1,\"colwidth\":null},\"content\":[{\"type\":\"paragraph\",\"attrs\":{\"textAlign\":null},\"content\":[{\"type\":\"text\",\"text\":\"Шаблон\"}]}]},{\"type\":\"tableCell\",\"attrs\":{\"colspan\":1,\"rowspan\":1,\"colwidth\":null},\"content\":[{\"type\":\"paragraph\",\"attrs\":{\"textAlign\":null},\"content\":[{\"type\":\"text\",\"text\":\"Запущенный экземпляр\"}]}]}]},{\"type\":\"tableRow\",\"content\":[{\"type\":\"tableCell\",\"attrs\":{\"colspan\":1,\"rowspan\":1,\"colwidth\":null},\"content\":[{\"type\":\"paragraph\",\"attrs\":{\"textAlign\":null},\"content\":[{\"type\":\"text\",\"text\":\"Immutable\"}]}]},{\"type\":\"tableCell\",\"attrs\":{\"colspan\":1,\"rowspan\":1,\"colwidth\":null},\"content\":[{\"type\":\"paragraph\",\"attrs\":{\"textAlign\":null},\"content\":[{\"type\":\"text\",\"text\":\"Изменяем при работе\"}]}]}]},{\"type\":\"tableRow\",\"content\":[{\"type\":\"tableCell\",\"attrs\":{\"colspan\":1,\"rowspan\":1,\"colwidth\":null},\"content\":[{\"type\":\"paragraph\",\"attrs\":{\"textAlign\":null},\"content\":[{\"type\":\"text\",\"text\":\"Хранится\"}]}]},{\"type\":\"tableCell\",\"attrs\":{\"colspan\":1,\"rowspan\":1,\"colwidth\":null},\"content\":[{\"type\":\"paragraph\",\"attrs\":{\"textAlign\":null},\"content\":[{\"type\":\"text\",\"text\":\"Выполняется\"}]}]}]}]},{\"type\":\"horizontalRule\"},{\"type\":\"paragraph\",\"attrs\":{\"textAlign\":null},\"content\":[{\"type\":\"text\",\"marks\":[{\"type\":\"bold\"}],\"text\":\"Итог:\"},{\"type\":\"text\",\"text\":\" образ — это основа, контейнер — это его запускаемая «живая» копия в изоляции.\"}]}]}",
        "grade": "trainee",
        "language": null,
        "generationSource": "USER",
        "framework": null,
        "expectedAnswer": null,
        "categoryId": 192,
        "createdAt": "2025-10-22T08:01:23.011Z",
        "updatedAt": "2025-10-22T08:01:23.011Z",
        "favoriteByUsers": [],
        "userProgress": [],
        "category": {
          "id": 192,
          "title": "Docker образы (images)",
          "directions": [
            {
              "categoryId": 192,
              "directionId": 5,
              "direction": {
                "id": 5,
                "title": "Инструменты и технологии",
                "order": 5,
                "isReady": true,
                "isVisible": true,
                "languages": [],
                "hasGrades": null,
                "frameworks": [],
                "createdAt": "2025-09-07T10:01:35.439Z",
                "updatedAt": "2025-11-26T11:09:24.423Z"
              }
            }
          ],
          "parent": {
            "title": "Docker",
            "id": 164,
            "parent": null
          }
        }
      },
      "previous": {
        "title": "Что такое Docker образ?",
        "id": 1855,
        "premium": false,
        "category": {
          "id": 192,
          "parent": {
            "title": "Docker",
            "id": 164,
            "parent": null
          },
          "directions": [
            {
              "directionId": 5
            }
          ]
        }
      },
      "next": {
        "title": "Что такое слой (layer) в Docker образе?",
        "id": 1857,
        "premium": true,
        "category": {
          "id": 192,
          "parent": {
            "title": "Docker",
            "id": 164,
            "parent": null
          },
          "directions": [
            {
              "directionId": 5
            }
          ]
        }
      }
    },
    {
      "current": {
        "id": 1857,
        "type": "boolean",
        "text": "{\"type\":\"doc\",\"content\":[{\"type\":\"paragraph\",\"attrs\":{\"textAlign\":null},\"content\":[{\"type\":\"text\",\"text\":\"Что такое слой (layer) в Docker образе? (junior)\"}]}]}",
        "title": "Что такое слой (layer) в Docker образе?",
        "order": 500102,
        "premium": true,
        "isPopular": false,
        "explanation": "{\"type\":\"doc\",\"content\":[{\"type\":\"paragraph\",\"attrs\":{\"textAlign\":null},\"content\":[{\"type\":\"text\",\"text\":\"Слой (layer) в Docker-образе — это часть образа, которая создаётся при выполнении каждой инструкции в \"},{\"type\":\"text\",\"marks\":[{\"type\":\"code\"}],\"text\":\"Dockerfile\"},{\"type\":\"text\",\"text\":\" (например: \"},{\"type\":\"text\",\"marks\":[{\"type\":\"code\"}],\"text\":\"FROM\"},{\"type\":\"text\",\"text\":\", \"},{\"type\":\"text\",\"marks\":[{\"type\":\"code\"}],\"text\":\"RUN\"},{\"type\":\"text\",\"text\":\", \"},{\"type\":\"text\",\"marks\":[{\"type\":\"code\"}],\"text\":\"COPY\"},{\"type\":\"text\",\"text\":\"). Каждый слой содержит изменения в файловой системе, которые добавляются поверх предыдущих.\"}]},{\"type\":\"horizontalRule\"},{\"type\":\"heading\",\"attrs\":{\"textAlign\":null,\"level\":3},\"content\":[{\"type\":\"text\",\"marks\":[{\"type\":\"bold\"}],\"text\":\"Как это понимать на уровне junior\"}]},{\"type\":\"bulletList\",\"content\":[{\"type\":\"listItem\",\"content\":[{\"type\":\"paragraph\",\"attrs\":{\"textAlign\":null},\"content\":[{\"type\":\"text\",\"text\":\"Образ собирается \"},{\"type\":\"text\",\"marks\":[{\"type\":\"bold\"}],\"text\":\"как пирог из слоёв\"},{\"type\":\"text\",\"text\":\" — один слой за другим.\"}]}]},{\"type\":\"listItem\",\"content\":[{\"type\":\"paragraph\",\"attrs\":{\"textAlign\":null},\"content\":[{\"type\":\"text\",\"text\":\"Если изменить одну команду, Docker \"},{\"type\":\"text\",\"marks\":[{\"type\":\"bold\"}],\"text\":\"пересоберёт только соответствующий слой\"},{\"type\":\"text\",\"text\":\", а остальные возьмёт из кэша — поэтому сборка быстрая.\"}]}]},{\"type\":\"listItem\",\"content\":[{\"type\":\"paragraph\",\"attrs\":{\"textAlign\":null},\"content\":[{\"type\":\"text\",\"text\":\"Все образы используют слои повторно. Например, разные образы с Ubuntu могут \"},{\"type\":\"text\",\"marks\":[{\"type\":\"bold\"}],\"text\":\"делить общий базовый слой\"},{\"type\":\"text\",\"text\":\", экономя место.\"}]}]}]},{\"type\":\"horizontalRule\"},{\"type\":\"heading\",\"attrs\":{\"textAlign\":null,\"level\":3},\"content\":[{\"type\":\"text\",\"marks\":[{\"type\":\"bold\"}],\"text\":\"Важные свойства слоёв\"}]},{\"type\":\"table\",\"content\":[{\"type\":\"tableRow\",\"content\":[{\"type\":\"tableHeader\",\"attrs\":{\"colspan\":1,\"rowspan\":1,\"colwidth\":null},\"content\":[{\"type\":\"paragraph\",\"attrs\":{\"textAlign\":null},\"content\":[{\"type\":\"text\",\"text\":\"Свойство\"}]}]},{\"type\":\"tableHeader\",\"attrs\":{\"colspan\":1,\"rowspan\":1,\"colwidth\":null},\"content\":[{\"type\":\"paragraph\",\"attrs\":{\"textAlign\":null},\"content\":[{\"type\":\"text\",\"text\":\"Объяснение\"}]}]}]},{\"type\":\"tableRow\",\"content\":[{\"type\":\"tableCell\",\"attrs\":{\"colspan\":1,\"rowspan\":1,\"colwidth\":null},\"content\":[{\"type\":\"paragraph\",\"attrs\":{\"textAlign\":null},\"content\":[{\"type\":\"text\",\"text\":\"Read-only\"}]}]},{\"type\":\"tableCell\",\"attrs\":{\"colspan\":1,\"rowspan\":1,\"colwidth\":null},\"content\":[{\"type\":\"paragraph\",\"attrs\":{\"textAlign\":null},\"content\":[{\"type\":\"text\",\"text\":\"Слой нельзя изменить — только добавить новый сверху\"}]}]}]},{\"type\":\"tableRow\",\"content\":[{\"type\":\"tableCell\",\"attrs\":{\"colspan\":1,\"rowspan\":1,\"colwidth\":null},\"content\":[{\"type\":\"paragraph\",\"attrs\":{\"textAlign\":null},\"content\":[{\"type\":\"text\",\"text\":\"Кэшируемый\"}]}]},{\"type\":\"tableCell\",\"attrs\":{\"colspan\":1,\"rowspan\":1,\"colwidth\":null},\"content\":[{\"type\":\"paragraph\",\"attrs\":{\"textAlign\":null},\"content\":[{\"type\":\"text\",\"text\":\"Если слой уже есть, Docker его не пересобирает\"}]}]}]},{\"type\":\"tableRow\",\"content\":[{\"type\":\"tableCell\",\"attrs\":{\"colspan\":1,\"rowspan\":1,\"colwidth\":null},\"content\":[{\"type\":\"paragraph\",\"attrs\":{\"textAlign\":null},\"content\":[{\"type\":\"text\",\"text\":\"Общий\"}]}]},{\"type\":\"tableCell\",\"attrs\":{\"colspan\":1,\"rowspan\":1,\"colwidth\":null},\"content\":[{\"type\":\"paragraph\",\"attrs\":{\"textAlign\":null},\"content\":[{\"type\":\"text\",\"text\":\"Один слой может использоваться многими образами\"}]}]}]}]},{\"type\":\"horizontalRule\"},{\"type\":\"paragraph\",\"attrs\":{\"textAlign\":null},\"content\":[{\"type\":\"text\",\"marks\":[{\"type\":\"bold\"}],\"text\":\"В одной фразе:\"},{\"type\":\"hardBreak\"},{\"type\":\"text\",\"marks\":[{\"type\":\"bold\"}],\"text\":\"Layer — это отдельный неизменяемый кусок образа, созданный из команды Dockerfile, который Docker может кэшировать и переиспользовать.\"}]}]}",
        "grade": "junior",
        "language": null,
        "generationSource": "USER",
        "framework": null,
        "expectedAnswer": null,
        "categoryId": 192,
        "createdAt": "2025-10-22T08:01:37.000Z",
        "updatedAt": "2025-11-10T13:17:06.874Z",
        "favoriteByUsers": [],
        "userProgress": [],
        "category": {
          "id": 192,
          "title": "Docker образы (images)",
          "directions": [
            {
              "categoryId": 192,
              "directionId": 5,
              "direction": {
                "id": 5,
                "title": "Инструменты и технологии",
                "order": 5,
                "isReady": true,
                "isVisible": true,
                "languages": [],
                "hasGrades": null,
                "frameworks": [],
                "createdAt": "2025-09-07T10:01:35.439Z",
                "updatedAt": "2025-11-26T11:09:24.423Z"
              }
            }
          ],
          "parent": {
            "title": "Docker",
            "id": 164,
            "parent": null
          }
        }
      },
      "previous": {
        "title": "Чем Docker образ отличается от контейнера?",
        "id": 1856,
        "premium": false,
        "category": {
          "id": 192,
          "parent": {
            "title": "Docker",
            "id": 164,
            "parent": null
          },
          "directions": [
            {
              "directionId": 5
            }
          ]
        }
      },
      "next": {
        "title": "Что означает «иммутабельность образа»?",
        "id": 1858,
        "premium": false,
        "category": {
          "id": 192,
          "parent": {
            "title": "Docker",
            "id": 164,
            "parent": null
          },
          "directions": [
            {
              "directionId": 5
            }
          ]
        }
      }
    },
    {
      "current": {
        "id": 1858,
        "type": "boolean",
        "text": "{\"type\":\"doc\",\"content\":[{\"type\":\"paragraph\",\"attrs\":{\"textAlign\":null},\"content\":[{\"type\":\"text\",\"text\":\"Что означает «иммутабельность образа»? (junior)\"}]}]}",
        "title": "Что означает «иммутабельность образа»?",
        "order": 500103,
        "premium": false,
        "isPopular": false,
        "explanation": "{\"type\":\"doc\",\"content\":[{\"type\":\"paragraph\",\"attrs\":{\"textAlign\":null},\"content\":[{\"type\":\"text\",\"text\":\"Иммутабельность образа означает, что \"},{\"type\":\"text\",\"marks\":[{\"type\":\"bold\"}],\"text\":\"образ нельзя изменить после его создания\"},{\"type\":\"text\",\"text\":\". Он «заморожен» в том виде, в котором был собран. Если нужно что-то поменять (добавить пакет, обновить конфиг и т.п.), Docker \"},{\"type\":\"text\",\"marks\":[{\"type\":\"bold\"}],\"text\":\"не редактирует старый образ\"},{\"type\":\"text\",\"text\":\", а \"},{\"type\":\"text\",\"marks\":[{\"type\":\"bold\"}],\"text\":\"создаёт новый на его основе\"},{\"type\":\"text\",\"text\":\".\"}]},{\"type\":\"horizontalRule\"},{\"type\":\"heading\",\"attrs\":{\"textAlign\":null,\"level\":3},\"content\":[{\"type\":\"text\",\"marks\":[{\"type\":\"bold\"}],\"text\":\"Зачем это нужно (junior-уровень)\"}]},{\"type\":\"bulletList\",\"content\":[{\"type\":\"listItem\",\"content\":[{\"type\":\"paragraph\",\"attrs\":{\"textAlign\":null},\"content\":[{\"type\":\"text\",\"marks\":[{\"type\":\"bold\"}],\"text\":\"Предсказуемость\"},{\"type\":\"text\",\"text\":\" — один и тот же образ всегда запускается одинаково.\"}]}]},{\"type\":\"listItem\",\"content\":[{\"type\":\"paragraph\",\"attrs\":{\"textAlign\":null},\"content\":[{\"type\":\"text\",\"marks\":[{\"type\":\"bold\"}],\"text\":\"Повторяемость\"},{\"type\":\"text\",\"text\":\" — легко воспроизвести окружение на любой машине.\"}]}]},{\"type\":\"listItem\",\"content\":[{\"type\":\"paragraph\",\"attrs\":{\"textAlign\":null},\"content\":[{\"type\":\"text\",\"marks\":[{\"type\":\"bold\"}],\"text\":\"Безопасность и контроль версий\"},{\"type\":\"text\",\"text\":\" — можно хранить \"},{\"type\":\"text\",\"marks\":[{\"type\":\"code\"}],\"text\":\"v1\"},{\"type\":\"text\",\"text\":\", \"},{\"type\":\"text\",\"marks\":[{\"type\":\"code\"}],\"text\":\"v2\"},{\"type\":\"text\",\"text\":\", \"},{\"type\":\"text\",\"marks\":[{\"type\":\"code\"}],\"text\":\"v3\"},{\"type\":\"text\",\"text\":\" и понимать, что внутри, без неожиданных изменений.\"}]}]}]},{\"type\":\"horizontalRule\"},{\"type\":\"paragraph\",\"attrs\":{\"textAlign\":null},\"content\":[{\"type\":\"text\",\"marks\":[{\"type\":\"bold\"}],\"text\":\"Если коротко:\"},{\"type\":\"hardBreak\"},{\"type\":\"text\",\"text\":\"Иммутабельность = \"},{\"type\":\"text\",\"marks\":[{\"type\":\"bold\"}],\"text\":\"образ нельзя менять, можно только собирать новый\"},{\"type\":\"text\",\"text\":\", поэтому он всегда остаётся стабильным и предсказуемым.\"}]}]}",
        "grade": "junior",
        "language": null,
        "generationSource": "USER",
        "framework": null,
        "expectedAnswer": null,
        "categoryId": 192,
        "createdAt": "2025-10-22T08:01:49.336Z",
        "updatedAt": "2025-10-22T08:04:34.313Z",
        "favoriteByUsers": [],
        "userProgress": [],
        "category": {
          "id": 192,
          "title": "Docker образы (images)",
          "directions": [
            {
              "categoryId": 192,
              "directionId": 5,
              "direction": {
                "id": 5,
                "title": "Инструменты и технологии",
                "order": 5,
                "isReady": true,
                "isVisible": true,
                "languages": [],
                "hasGrades": null,
                "frameworks": [],
                "createdAt": "2025-09-07T10:01:35.439Z",
                "updatedAt": "2025-11-26T11:09:24.423Z"
              }
            }
          ],
          "parent": {
            "title": "Docker",
            "id": 164,
            "parent": null
          }
        }
      },
      "previous": {
        "title": "Что такое слой (layer) в Docker образе?",
        "id": 1857,
        "premium": true,
        "category": {
          "id": 192,
          "parent": {
            "title": "Docker",
            "id": 164,
            "parent": null
          },
          "directions": [
            {
              "directionId": 5
            }
          ]
        }
      },
      "next": {
        "title": "Как создать docker образ?",
        "id": 1859,
        "premium": false,
        "category": {
          "id": 192,
          "parent": {
            "title": "Docker",
            "id": 164,
            "parent": null
          },
          "directions": [
            {
              "directionId": 5
            }
          ]
        }
      }
    },
    {
      "current": {
        "id": 1859,
        "type": "boolean",
        "text": "{\"type\":\"doc\",\"content\":[{\"type\":\"paragraph\",\"attrs\":{\"textAlign\":null},\"content\":[{\"type\":\"text\",\"text\":\"Как создать docker образ?\"}]}]}",
        "title": "Как создать docker образ?",
        "order": 500104,
        "premium": false,
        "isPopular": false,
        "explanation": "{\"type\":\"doc\",\"content\":[{\"type\":\"paragraph\",\"attrs\":{\"textAlign\":null},\"content\":[{\"type\":\"text\",\"text\":\"Создание Docker-образа обычно делается через \"},{\"type\":\"text\",\"marks\":[{\"type\":\"code\"}],\"text\":\"Dockerfile\"},{\"type\":\"text\",\"text\":\". Процесс состоит из трёх шагов:\"}]},{\"type\":\"horizontalRule\"},{\"type\":\"heading\",\"attrs\":{\"textAlign\":null,\"level\":3},\"content\":[{\"type\":\"text\",\"marks\":[{\"type\":\"bold\"}],\"text\":\"1. Создаёшь \"},{\"type\":\"text\",\"marks\":[{\"type\":\"code\"}],\"text\":\"Dockerfile\"}]},{\"type\":\"paragraph\",\"attrs\":{\"textAlign\":null},\"content\":[{\"type\":\"text\",\"text\":\"Например, для простого Python-приложения:\"}]},{\"type\":\"codeBlock\",\"attrs\":{\"language\":\"Dockerfile\"},\"content\":[{\"type\":\"text\",\"text\":\"FROM python:3.10\\nWORKDIR /app\\nCOPY . .\\nRUN pip install -r requirements.txt\\nCMD [\\\"python\\\", \\\"app.py\\\"]\\n\"}]},{\"type\":\"horizontalRule\"},{\"type\":\"heading\",\"attrs\":{\"textAlign\":null,\"level\":3},\"content\":[{\"type\":\"text\",\"marks\":[{\"type\":\"bold\"}],\"text\":\"2. Собираешь образ командой\"}]},{\"type\":\"paragraph\",\"attrs\":{\"textAlign\":null},\"content\":[{\"type\":\"text\",\"text\":\"Находясь в папке с \"},{\"type\":\"text\",\"marks\":[{\"type\":\"code\"}],\"text\":\"Dockerfile\"},{\"type\":\"text\",\"text\":\", выполняешь:\"}]},{\"type\":\"codeBlock\",\"attrs\":{\"language\":\"bash\"},\"content\":[{\"type\":\"text\",\"text\":\"docker build -t myapp:1.0 .\\n\"}]},{\"type\":\"paragraph\",\"attrs\":{\"textAlign\":null},\"content\":[{\"type\":\"text\",\"text\":\"Где:\"}]},{\"type\":\"bulletList\",\"content\":[{\"type\":\"listItem\",\"content\":[{\"type\":\"paragraph\",\"attrs\":{\"textAlign\":null},\"content\":[{\"type\":\"text\",\"marks\":[{\"type\":\"code\"}],\"text\":\"docker build\"},{\"type\":\"text\",\"text\":\" — команда сборки\"}]}]},{\"type\":\"listItem\",\"content\":[{\"type\":\"paragraph\",\"attrs\":{\"textAlign\":null},\"content\":[{\"type\":\"text\",\"marks\":[{\"type\":\"code\"}],\"text\":\"-t myapp:1.0\"},{\"type\":\"text\",\"text\":\" — имя и тег образа\"}]}]},{\"type\":\"listItem\",\"content\":[{\"type\":\"paragraph\",\"attrs\":{\"textAlign\":null},\"content\":[{\"type\":\"text\",\"marks\":[{\"type\":\"code\"}],\"text\":\".\"},{\"type\":\"text\",\"text\":\" — контекст сборки (текущая папка)\"}]}]}]},{\"type\":\"horizontalRule\"},{\"type\":\"heading\",\"attrs\":{\"textAlign\":null,\"level\":3},\"content\":[{\"type\":\"text\",\"marks\":[{\"type\":\"bold\"}],\"text\":\"3. Проверяешь и запускаешь контейнер\"}]},{\"type\":\"paragraph\",\"attrs\":{\"textAlign\":null},\"content\":[{\"type\":\"text\",\"text\":\"Запуск контейнера из собранного образа:\"}]},{\"type\":\"codeBlock\",\"attrs\":{\"language\":\"bash\"},\"content\":[{\"type\":\"text\",\"text\":\"docker run --name mycontainer myapp:1.0\\n\"}]},{\"type\":\"horizontalRule\"},{\"type\":\"heading\",\"attrs\":{\"textAlign\":null,\"level\":3},\"content\":[{\"type\":\"text\",\"marks\":[{\"type\":\"bold\"}],\"text\":\"Итог\"}]},{\"type\":\"table\",\"content\":[{\"type\":\"tableRow\",\"content\":[{\"type\":\"tableHeader\",\"attrs\":{\"colspan\":1,\"rowspan\":1,\"colwidth\":null},\"content\":[{\"type\":\"paragraph\",\"attrs\":{\"textAlign\":null},\"content\":[{\"type\":\"text\",\"text\":\"Действие\"}]}]},{\"type\":\"tableHeader\",\"attrs\":{\"colspan\":1,\"rowspan\":1,\"colwidth\":null},\"content\":[{\"type\":\"paragraph\",\"attrs\":{\"textAlign\":null},\"content\":[{\"type\":\"text\",\"text\":\"Команда\"}]}]}]},{\"type\":\"tableRow\",\"content\":[{\"type\":\"tableCell\",\"attrs\":{\"colspan\":1,\"rowspan\":1,\"colwidth\":null},\"content\":[{\"type\":\"paragraph\",\"attrs\":{\"textAlign\":null},\"content\":[{\"type\":\"text\",\"text\":\"Создать образ\"}]}]},{\"type\":\"tableCell\",\"attrs\":{\"colspan\":1,\"rowspan\":1,\"colwidth\":null},\"content\":[{\"type\":\"paragraph\",\"attrs\":{\"textAlign\":null},\"content\":[{\"type\":\"text\",\"marks\":[{\"type\":\"code\"}],\"text\":\"docker build -t name:tag .\"}]}]}]},{\"type\":\"tableRow\",\"content\":[{\"type\":\"tableCell\",\"attrs\":{\"colspan\":1,\"rowspan\":1,\"colwidth\":null},\"content\":[{\"type\":\"paragraph\",\"attrs\":{\"textAlign\":null},\"content\":[{\"type\":\"text\",\"text\":\"Посмотреть список образов\"}]}]},{\"type\":\"tableCell\",\"attrs\":{\"colspan\":1,\"rowspan\":1,\"colwidth\":null},\"content\":[{\"type\":\"paragraph\",\"attrs\":{\"textAlign\":null},\"content\":[{\"type\":\"text\",\"marks\":[{\"type\":\"code\"}],\"text\":\"docker images\"}]}]}]},{\"type\":\"tableRow\",\"content\":[{\"type\":\"tableCell\",\"attrs\":{\"colspan\":1,\"rowspan\":1,\"colwidth\":null},\"content\":[{\"type\":\"paragraph\",\"attrs\":{\"textAlign\":null},\"content\":[{\"type\":\"text\",\"text\":\"Запустить контейнер\"}]}]},{\"type\":\"tableCell\",\"attrs\":{\"colspan\":1,\"rowspan\":1,\"colwidth\":null},\"content\":[{\"type\":\"paragraph\",\"attrs\":{\"textAlign\":null},\"content\":[{\"type\":\"text\",\"marks\":[{\"type\":\"code\"}],\"text\":\"docker run name:tag\"}]}]}]}]},{\"type\":\"horizontalRule\"},{\"type\":\"paragraph\",\"attrs\":{\"textAlign\":null},\"content\":[{\"type\":\"text\",\"text\":\"Если нужно, могу показать \"},{\"type\":\"text\",\"marks\":[{\"type\":\"bold\"}],\"text\":\"ещё более простой пример\"},{\"type\":\"text\",\"text\":\", \"},{\"type\":\"text\",\"marks\":[{\"type\":\"bold\"}],\"text\":\"пример для Node.js\"},{\"type\":\"text\",\"text\":\", или объяснить \"},{\"type\":\"text\",\"marks\":[{\"type\":\"bold\"}],\"text\":\"каждую строку Dockerfile построчно\"},{\"type\":\"text\",\"text\":\". Что выберем?\"}]}]}",
        "grade": "trainee",
        "language": null,
        "generationSource": "USER",
        "framework": null,
        "expectedAnswer": null,
        "categoryId": 192,
        "createdAt": "2025-10-22T08:02:02.314Z",
        "updatedAt": "2025-10-22T08:02:02.314Z",
        "favoriteByUsers": [],
        "userProgress": [],
        "category": {
          "id": 192,
          "title": "Docker образы (images)",
          "directions": [
            {
              "categoryId": 192,
              "directionId": 5,
              "direction": {
                "id": 5,
                "title": "Инструменты и технологии",
                "order": 5,
                "isReady": true,
                "isVisible": true,
                "languages": [],
                "hasGrades": null,
                "frameworks": [],
                "createdAt": "2025-09-07T10:01:35.439Z",
                "updatedAt": "2025-11-26T11:09:24.423Z"
              }
            }
          ],
          "parent": {
            "title": "Docker",
            "id": 164,
            "parent": null
          }
        }
      },
      "previous": {
        "title": "Что означает «иммутабельность образа»?",
        "id": 1858,
        "premium": false,
        "category": {
          "id": 192,
          "parent": {
            "title": "Docker",
            "id": 164,
            "parent": null
          },
          "directions": [
            {
              "directionId": 5
            }
          ]
        }
      },
      "next": {
        "title": "Как удалить docker образ?",
        "id": 1860,
        "premium": true,
        "category": {
          "id": 192,
          "parent": {
            "title": "Docker",
            "id": 164,
            "parent": null
          },
          "directions": [
            {
              "directionId": 5
            }
          ]
        }
      }
    },
    {
      "current": {
        "id": 1860,
        "type": "boolean",
        "text": "{\"type\":\"doc\",\"content\":[{\"type\":\"paragraph\",\"attrs\":{\"textAlign\":null},\"content\":[{\"type\":\"text\",\"text\":\"Как удалить docker образ?\"}]}]}",
        "title": "Как удалить docker образ?",
        "order": 500105,
        "premium": true,
        "isPopular": false,
        "explanation": "{\"type\":\"doc\",\"content\":[{\"type\":\"paragraph\",\"attrs\":{\"textAlign\":null},\"content\":[{\"type\":\"text\",\"text\":\"Удаление выполняется через команду \"},{\"type\":\"text\",\"marks\":[{\"type\":\"code\"}],\"text\":\"docker rmi\"},{\"type\":\"text\",\"text\":\".\"}]},{\"type\":\"horizontalRule\"},{\"type\":\"heading\",\"attrs\":{\"textAlign\":null,\"level\":3},\"content\":[{\"type\":\"text\",\"marks\":[{\"type\":\"bold\"}],\"text\":\"1. Посмотреть образы\"}]},{\"type\":\"codeBlock\",\"attrs\":{\"language\":\"bash\"},\"content\":[{\"type\":\"text\",\"text\":\"docker images\\n\"}]},{\"type\":\"horizontalRule\"},{\"type\":\"heading\",\"attrs\":{\"textAlign\":null,\"level\":3},\"content\":[{\"type\":\"text\",\"marks\":[{\"type\":\"bold\"}],\"text\":\"2. Удалить конкретный образ\"}]},{\"type\":\"codeBlock\",\"attrs\":{\"language\":\"bash\"},\"content\":[{\"type\":\"text\",\"text\":\"docker rmi IMAGE_NAME\\n\"}]},{\"type\":\"paragraph\",\"attrs\":{\"textAlign\":null},\"content\":[{\"type\":\"text\",\"text\":\"или по ID:\"}]},{\"type\":\"codeBlock\",\"attrs\":{\"language\":\"bash\"},\"content\":[{\"type\":\"text\",\"text\":\"docker rmi IMAGE_ID\\n\"}]},{\"type\":\"horizontalRule\"},{\"type\":\"heading\",\"attrs\":{\"textAlign\":null,\"level\":3},\"content\":[{\"type\":\"text\",\"marks\":[{\"type\":\"bold\"}],\"text\":\"3. Если образ используется контейнером\"}]},{\"type\":\"paragraph\",\"attrs\":{\"textAlign\":null},\"content\":[{\"type\":\"text\",\"text\":\"Сначала удалить контейнер:\"}]},{\"type\":\"codeBlock\",\"attrs\":{\"language\":\"bash\"},\"content\":[{\"type\":\"text\",\"text\":\"docker rm CONTAINER_ID\\n\"}]},{\"type\":\"paragraph\",\"attrs\":{\"textAlign\":null},\"content\":[{\"type\":\"text\",\"text\":\"А затем снова:\"}]},{\"type\":\"codeBlock\",\"attrs\":{\"language\":\"bash\"},\"content\":[{\"type\":\"text\",\"text\":\"docker rmi IMAGE_ID\\n\"}]},{\"type\":\"horizontalRule\"},{\"type\":\"heading\",\"attrs\":{\"textAlign\":null,\"level\":3},\"content\":[{\"type\":\"text\",\"marks\":[{\"type\":\"bold\"}],\"text\":\"4. Удалить все неиспользуемые образы\"}]},{\"type\":\"codeBlock\",\"attrs\":{\"language\":\"bash\"},\"content\":[{\"type\":\"text\",\"text\":\"docker image prune\\n\"}]},{\"type\":\"paragraph\",\"attrs\":{\"textAlign\":null},\"content\":[{\"type\":\"text\",\"text\":\"или радикально (всё неиспользуемое):\"}]},{\"type\":\"codeBlock\",\"attrs\":{\"language\":\"bash\"},\"content\":[{\"type\":\"text\",\"text\":\"docker system prune -a\\n\"}]},{\"type\":\"horizontalRule\"},{\"type\":\"paragraph\",\"attrs\":{\"textAlign\":null},\"content\":[{\"type\":\"text\",\"marks\":[{\"type\":\"bold\"}],\"text\":\"Главное правило:\"},{\"type\":\"text\",\"text\":\" пока контейнер создан или запущен из образа — образ не удалится.\"}]}]}",
        "grade": "trainee",
        "language": null,
        "generationSource": "USER",
        "framework": null,
        "expectedAnswer": null,
        "categoryId": 192,
        "createdAt": "2025-10-22T08:02:18.185Z",
        "updatedAt": "2025-11-10T13:17:10.169Z",
        "favoriteByUsers": [],
        "userProgress": [],
        "category": {
          "id": 192,
          "title": "Docker образы (images)",
          "directions": [
            {
              "categoryId": 192,
              "directionId": 5,
              "direction": {
                "id": 5,
                "title": "Инструменты и технологии",
                "order": 5,
                "isReady": true,
                "isVisible": true,
                "languages": [],
                "hasGrades": null,
                "frameworks": [],
                "createdAt": "2025-09-07T10:01:35.439Z",
                "updatedAt": "2025-11-26T11:09:24.423Z"
              }
            }
          ],
          "parent": {
            "title": "Docker",
            "id": 164,
            "parent": null
          }
        }
      },
      "previous": {
        "title": "Как создать docker образ?",
        "id": 1859,
        "premium": false,
        "category": {
          "id": 192,
          "parent": {
            "title": "Docker",
            "id": 164,
            "parent": null
          },
          "directions": [
            {
              "directionId": 5
            }
          ]
        }
      },
      "next": {
        "title": "Что такое тег Docker образа?",
        "id": 1861,
        "premium": false,
        "category": {
          "id": 192,
          "parent": {
            "title": "Docker",
            "id": 164,
            "parent": null
          },
          "directions": [
            {
              "directionId": 5
            }
          ]
        }
      }
    },
    {
      "current": {
        "id": 1861,
        "type": "boolean",
        "text": "{\"type\":\"doc\",\"content\":[{\"type\":\"paragraph\",\"attrs\":{\"textAlign\":null},\"content\":[{\"type\":\"text\",\"text\":\"Что такое тег Docker образа?\"}]}]}",
        "title": "Что такое тег Docker образа?",
        "order": 500106,
        "premium": false,
        "isPopular": false,
        "explanation": "{\"type\":\"doc\",\"content\":[{\"type\":\"paragraph\",\"attrs\":{\"textAlign\":null},\"content\":[{\"type\":\"text\",\"text\":\"Тег Docker-образа — это метка, которая присваивается образу, чтобы отличать его версии. Обычно тег используют как \"},{\"type\":\"text\",\"marks\":[{\"type\":\"bold\"}],\"text\":\"человеческое имя версии\"},{\"type\":\"text\",\"text\":\", например: \"},{\"type\":\"text\",\"marks\":[{\"type\":\"code\"}],\"text\":\"latest\"},{\"type\":\"text\",\"text\":\", \"},{\"type\":\"text\",\"marks\":[{\"type\":\"code\"}],\"text\":\"1.0\"},{\"type\":\"text\",\"text\":\", \"},{\"type\":\"text\",\"marks\":[{\"type\":\"code\"}],\"text\":\"dev\"},{\"type\":\"text\",\"text\":\", \"},{\"type\":\"text\",\"marks\":[{\"type\":\"code\"}],\"text\":\"prod\"},{\"type\":\"text\",\"text\":\".\"}]},{\"type\":\"horizontalRule\"},{\"type\":\"heading\",\"attrs\":{\"textAlign\":null,\"level\":3},\"content\":[{\"type\":\"text\",\"marks\":[{\"type\":\"bold\"}],\"text\":\"Как выглядит тег\"}]},{\"type\":\"codeBlock\",\"attrs\":{\"language\":\"bash\"},\"content\":[{\"type\":\"text\",\"text\":\"nginx:1.25\\npython:3.10\\nmyapp:latest\\n\"}]},{\"type\":\"paragraph\",\"attrs\":{\"textAlign\":null},\"content\":[{\"type\":\"text\",\"text\":\"Где:\"}]},{\"type\":\"bulletList\",\"content\":[{\"type\":\"listItem\",\"content\":[{\"type\":\"paragraph\",\"attrs\":{\"textAlign\":null},\"content\":[{\"type\":\"text\",\"marks\":[{\"type\":\"code\"}],\"text\":\"nginx\"},{\"type\":\"text\",\"text\":\", \"},{\"type\":\"text\",\"marks\":[{\"type\":\"code\"}],\"text\":\"python\"},{\"type\":\"text\",\"text\":\", \"},{\"type\":\"text\",\"marks\":[{\"type\":\"code\"}],\"text\":\"myapp\"},{\"type\":\"text\",\"text\":\" — имя образа\"}]}]},{\"type\":\"listItem\",\"content\":[{\"type\":\"paragraph\",\"attrs\":{\"textAlign\":null},\"content\":[{\"type\":\"text\",\"marks\":[{\"type\":\"code\"}],\"text\":\"1.25\"},{\"type\":\"text\",\"text\":\", \"},{\"type\":\"text\",\"marks\":[{\"type\":\"code\"}],\"text\":\"3.10\"},{\"type\":\"text\",\"text\":\", \"},{\"type\":\"text\",\"marks\":[{\"type\":\"code\"}],\"text\":\"latest\"},{\"type\":\"text\",\"text\":\" — тег\"}]}]}]},{\"type\":\"horizontalRule\"},{\"type\":\"heading\",\"attrs\":{\"textAlign\":null,\"level\":3},\"content\":[{\"type\":\"text\",\"marks\":[{\"type\":\"bold\"}],\"text\":\"Зачем нужен тег\"}]},{\"type\":\"bulletList\",\"content\":[{\"type\":\"listItem\",\"content\":[{\"type\":\"paragraph\",\"attrs\":{\"textAlign\":null},\"content\":[{\"type\":\"text\",\"text\":\"чтобы хранить \"},{\"type\":\"text\",\"marks\":[{\"type\":\"bold\"}],\"text\":\"несколько версий одного образа\"},{\"type\":\"text\",\"text\":\";\"}]}]},{\"type\":\"listItem\",\"content\":[{\"type\":\"paragraph\",\"attrs\":{\"textAlign\":null},\"content\":[{\"type\":\"text\",\"text\":\"чтобы \"},{\"type\":\"text\",\"marks\":[{\"type\":\"bold\"}],\"text\":\"деплой, тесты и разработка\"},{\"type\":\"text\",\"text\":\" работали предсказуемо;\"}]}]},{\"type\":\"listItem\",\"content\":[{\"type\":\"paragraph\",\"attrs\":{\"textAlign\":null},\"content\":[{\"type\":\"text\",\"text\":\"чтобы можно было \"},{\"type\":\"text\",\"marks\":[{\"type\":\"bold\"}],\"text\":\"вернуться к конкретной версии\"},{\"type\":\"text\",\"text\":\".\"}]}]}]},{\"type\":\"horizontalRule\"},{\"type\":\"heading\",\"attrs\":{\"textAlign\":null,\"level\":3},\"content\":[{\"type\":\"text\",\"marks\":[{\"type\":\"bold\"}],\"text\":\"Особенность\"}]},{\"type\":\"paragraph\",\"attrs\":{\"textAlign\":null},\"content\":[{\"type\":\"text\",\"text\":\"Если тег не указать, Docker \"},{\"type\":\"text\",\"marks\":[{\"type\":\"bold\"}],\"text\":\"по умолчанию подставит \"},{\"type\":\"text\",\"marks\":[{\"type\":\"code\"}],\"text\":\":latest\"},{\"type\":\"text\",\"text\":\".\"}]},{\"type\":\"horizontalRule\"},{\"type\":\"paragraph\",\"attrs\":{\"textAlign\":null},\"content\":[{\"type\":\"text\",\"marks\":[{\"type\":\"bold\"}],\"text\":\"Итог:\"},{\"type\":\"text\",\"text\":\" тег — это версия или метка образа, помогающая различать варианты одного и того же Docker-image.\"}]}]}",
        "grade": "trainee",
        "language": null,
        "generationSource": "USER",
        "framework": null,
        "expectedAnswer": null,
        "categoryId": 192,
        "createdAt": "2025-10-22T08:02:29.748Z",
        "updatedAt": "2025-10-22T08:02:29.748Z",
        "favoriteByUsers": [],
        "userProgress": [],
        "category": {
          "id": 192,
          "title": "Docker образы (images)",
          "directions": [
            {
              "categoryId": 192,
              "directionId": 5,
              "direction": {
                "id": 5,
                "title": "Инструменты и технологии",
                "order": 5,
                "isReady": true,
                "isVisible": true,
                "languages": [],
                "hasGrades": null,
                "frameworks": [],
                "createdAt": "2025-09-07T10:01:35.439Z",
                "updatedAt": "2025-11-26T11:09:24.423Z"
              }
            }
          ],
          "parent": {
            "title": "Docker",
            "id": 164,
            "parent": null
          }
        }
      },
      "previous": {
        "title": "Как удалить docker образ?",
        "id": 1860,
        "premium": true,
        "category": {
          "id": 192,
          "parent": {
            "title": "Docker",
            "id": 164,
            "parent": null
          },
          "directions": [
            {
              "directionId": 5
            }
          ]
        }
      },
      "next": {
        "title": "Что такое Dockerfile?",
        "id": 1862,
        "premium": false,
        "category": {
          "id": 192,
          "parent": {
            "title": "Docker",
            "id": 164,
            "parent": null
          },
          "directions": [
            {
              "directionId": 5
            }
          ]
        }
      }
    },
    {
      "current": {
        "id": 1862,
        "type": "boolean",
        "text": "{\"type\":\"doc\",\"content\":[{\"type\":\"paragraph\",\"attrs\":{\"textAlign\":null},\"content\":[{\"type\":\"text\",\"text\":\"Что такое Dockerfile?\"}]}]}",
        "title": "Что такое Dockerfile?",
        "order": 500107,
        "premium": false,
        "isPopular": false,
        "explanation": "{\"type\":\"doc\",\"content\":[{\"type\":\"paragraph\",\"attrs\":{\"textAlign\":null},\"content\":[{\"type\":\"text\",\"text\":\"Dockerfile — это текстовый файл с набором инструкций, которые описывают, \"},{\"type\":\"text\",\"marks\":[{\"type\":\"bold\"}],\"text\":\"как собрать Docker-образ\"},{\"type\":\"text\",\"text\":\". Каждая строка в Dockerfile — это шаг сборки (установка зависимостей, копирование файлов, запуск команд и т.д.).\"}]},{\"type\":\"horizontalRule\"},{\"type\":\"heading\",\"attrs\":{\"textAlign\":null,\"level\":3},\"content\":[{\"type\":\"text\",\"marks\":[{\"type\":\"bold\"}],\"text\":\"Что делает Dockerfile\"}]},{\"type\":\"bulletList\",\"content\":[{\"type\":\"listItem\",\"content\":[{\"type\":\"paragraph\",\"attrs\":{\"textAlign\":null},\"content\":[{\"type\":\"text\",\"text\":\"задаёт базовый образ (например, \"},{\"type\":\"text\",\"marks\":[{\"type\":\"code\"}],\"text\":\"ubuntu\"},{\"type\":\"text\",\"text\":\" или \"},{\"type\":\"text\",\"marks\":[{\"type\":\"code\"}],\"text\":\"python:3.10\"},{\"type\":\"text\",\"text\":\");\"}]}]},{\"type\":\"listItem\",\"content\":[{\"type\":\"paragraph\",\"attrs\":{\"textAlign\":null},\"content\":[{\"type\":\"text\",\"text\":\"копирует файлы проекта внутрь будущего образа;\"}]}]},{\"type\":\"listItem\",\"content\":[{\"type\":\"paragraph\",\"attrs\":{\"textAlign\":null},\"content\":[{\"type\":\"text\",\"text\":\"устанавливает зависимости;\"}]}]},{\"type\":\"listItem\",\"content\":[{\"type\":\"paragraph\",\"attrs\":{\"textAlign\":null},\"content\":[{\"type\":\"text\",\"text\":\"настраивает рабочую директорию и переменные среды;\"}]}]},{\"type\":\"listItem\",\"content\":[{\"type\":\"paragraph\",\"attrs\":{\"textAlign\":null},\"content\":[{\"type\":\"text\",\"text\":\"указывает команду, которая будет выполняться при запуске контейнера.\"}]}]}]},{\"type\":\"horizontalRule\"},{\"type\":\"heading\",\"attrs\":{\"textAlign\":null,\"level\":3},\"content\":[{\"type\":\"text\",\"marks\":[{\"type\":\"bold\"}],\"text\":\"Простейший пример Dockerfile\"}]},{\"type\":\"codeBlock\",\"attrs\":{\"language\":\"Dockerfile\"},\"content\":[{\"type\":\"text\",\"text\":\"FROM python:3.10\\nWORKDIR /app\\nCOPY . .\\nRUN pip install -r requirements.txt\\nCMD [\\\"python\\\", \\\"app.py\\\"]\\n\"}]},{\"type\":\"horizontalRule\"},{\"type\":\"heading\",\"attrs\":{\"textAlign\":null,\"level\":3},\"content\":[{\"type\":\"text\",\"marks\":[{\"type\":\"bold\"}],\"text\":\"Как используется\"}]},{\"type\":\"orderedList\",\"attrs\":{\"start\":1,\"type\":null},\"content\":[{\"type\":\"listItem\",\"content\":[{\"type\":\"paragraph\",\"attrs\":{\"textAlign\":null},\"content\":[{\"type\":\"text\",\"text\":\"Пишем Dockerfile\"}]}]},{\"type\":\"listItem\",\"content\":[{\"type\":\"paragraph\",\"attrs\":{\"textAlign\":null},\"content\":[{\"type\":\"text\",\"text\":\"Собираем образ:\"}]},{\"type\":\"codeBlock\",\"attrs\":{\"language\":\"bash\"},\"content\":[{\"type\":\"text\",\"text\":\"docker build -t myapp .\\n\"}]}]},{\"type\":\"listItem\",\"content\":[{\"type\":\"paragraph\",\"attrs\":{\"textAlign\":null},\"content\":[{\"type\":\"text\",\"text\":\"Запускаем контейнер:\"}]},{\"type\":\"codeBlock\",\"attrs\":{\"language\":\"bash\"},\"content\":[{\"type\":\"text\",\"text\":\"docker run myapp\\n\"}]}]}]},{\"type\":\"horizontalRule\"},{\"type\":\"paragraph\",\"attrs\":{\"textAlign\":null},\"content\":[{\"type\":\"text\",\"marks\":[{\"type\":\"bold\"}],\"text\":\"Коротко:\"},{\"type\":\"text\",\"text\":\" Dockerfile — это рецепт. Docker-образ — готовое блюдо. Контейнер — запущенный экземпляр этого «блюда» в работе.\"}]}]}",
        "grade": "trainee",
        "language": null,
        "generationSource": "USER",
        "framework": null,
        "expectedAnswer": null,
        "categoryId": 192,
        "createdAt": "2025-10-22T08:02:52.234Z",
        "updatedAt": "2025-10-22T08:02:52.234Z",
        "favoriteByUsers": [],
        "userProgress": [],
        "category": {
          "id": 192,
          "title": "Docker образы (images)",
          "directions": [
            {
              "categoryId": 192,
              "directionId": 5,
              "direction": {
                "id": 5,
                "title": "Инструменты и технологии",
                "order": 5,
                "isReady": true,
                "isVisible": true,
                "languages": [],
                "hasGrades": null,
                "frameworks": [],
                "createdAt": "2025-09-07T10:01:35.439Z",
                "updatedAt": "2025-11-26T11:09:24.423Z"
              }
            }
          ],
          "parent": {
            "title": "Docker",
            "id": 164,
            "parent": null
          }
        }
      },
      "previous": {
        "title": "Что такое тег Docker образа?",
        "id": 1861,
        "premium": false,
        "category": {
          "id": 192,
          "parent": {
            "title": "Docker",
            "id": 164,
            "parent": null
          },
          "directions": [
            {
              "directionId": 5
            }
          ]
        }
      },
      "next": {
        "title": "Что такое базовый образ (base image)? ",
        "id": 1863,
        "premium": true,
        "category": {
          "id": 192,
          "parent": {
            "title": "Docker",
            "id": 164,
            "parent": null
          },
          "directions": [
            {
              "directionId": 5
            }
          ]
        }
      }
    },
    {
      "current": {
        "id": 1863,
        "type": "boolean",
        "text": "{\"type\":\"doc\",\"content\":[{\"type\":\"paragraph\",\"attrs\":{\"textAlign\":null},\"content\":[{\"type\":\"text\",\"text\":\"Что такое базовый образ (base image)?\"}]}]}",
        "title": "Что такое базовый образ (base image)? ",
        "order": 500108,
        "premium": true,
        "isPopular": false,
        "explanation": "{\"type\":\"doc\",\"content\":[{\"type\":\"paragraph\",\"attrs\":{\"textAlign\":null},\"content\":[{\"type\":\"text\",\"text\":\"Базовый образ (base image) — это исходный образ, \"},{\"type\":\"text\",\"marks\":[{\"type\":\"bold\"}],\"text\":\"от которого начинается сборка Docker-образа\"},{\"type\":\"text\",\"text\":\". Он задаёт стартовую файловую систему и окружение, поверх которых добавляются слои с приложением и зависимостями.\"}]},{\"type\":\"horizontalRule\"},{\"type\":\"heading\",\"attrs\":{\"textAlign\":null,\"level\":3},\"content\":[{\"type\":\"text\",\"marks\":[{\"type\":\"bold\"}],\"text\":\"Пример для понимания\"}]},{\"type\":\"paragraph\",\"attrs\":{\"textAlign\":null},\"content\":[{\"type\":\"text\",\"text\":\"В Dockerfile строка:\"}]},{\"type\":\"codeBlock\",\"attrs\":{\"language\":\"Dockerfile\"},\"content\":[{\"type\":\"text\",\"text\":\"FROM ubuntu:22.04\\n\"}]},{\"type\":\"paragraph\",\"attrs\":{\"textAlign\":null},\"content\":[{\"type\":\"text\",\"text\":\"означает, что базой будет Ubuntu, а дальше мы будем накладывать свои слои: копировать файлы, устанавливать пакеты и т.д.\"}]},{\"type\":\"horizontalRule\"},{\"type\":\"heading\",\"attrs\":{\"textAlign\":null,\"level\":3},\"content\":[{\"type\":\"text\",\"marks\":[{\"type\":\"bold\"}],\"text\":\"Каким может быть base image\"}]},{\"type\":\"orderedList\",\"attrs\":{\"start\":1,\"type\":null},\"content\":[{\"type\":\"listItem\",\"content\":[{\"type\":\"paragraph\",\"attrs\":{\"textAlign\":null},\"content\":[{\"type\":\"text\",\"marks\":[{\"type\":\"bold\"}],\"text\":\"ОС как основа\"},{\"type\":\"hardBreak\"},{\"type\":\"text\",\"marks\":[{\"type\":\"code\"}],\"text\":\"ubuntu\"},{\"type\":\"text\",\"text\":\", \"},{\"type\":\"text\",\"marks\":[{\"type\":\"code\"}],\"text\":\"alpine\"},{\"type\":\"text\",\"text\":\", \"},{\"type\":\"text\",\"marks\":[{\"type\":\"code\"}],\"text\":\"debian\"},{\"type\":\"text\",\"text\":\" — минимальная система для приложений.\"}]}]},{\"type\":\"listItem\",\"content\":[{\"type\":\"paragraph\",\"attrs\":{\"textAlign\":null},\"content\":[{\"type\":\"text\",\"marks\":[{\"type\":\"bold\"}],\"text\":\"Языковая основа\"},{\"type\":\"hardBreak\"},{\"type\":\"text\",\"marks\":[{\"type\":\"code\"}],\"text\":\"python:3.10\"},{\"type\":\"text\",\"text\":\", \"},{\"type\":\"text\",\"marks\":[{\"type\":\"code\"}],\"text\":\"node:18\"},{\"type\":\"text\",\"text\":\", \"},{\"type\":\"text\",\"marks\":[{\"type\":\"code\"}],\"text\":\"openjdk:17\"},{\"type\":\"text\",\"text\":\" — уже предустановленные рантаймы.\"}]}]},{\"type\":\"listItem\",\"content\":[{\"type\":\"paragraph\",\"attrs\":{\"textAlign\":null},\"content\":[{\"type\":\"text\",\"marks\":[{\"type\":\"bold\"}],\"text\":\"Пустая основа (scratch)\"},{\"type\":\"hardBreak\"},{\"type\":\"text\",\"marks\":[{\"type\":\"code\"}],\"text\":\"FROM scratch\"},{\"type\":\"text\",\"text\":\" — полностью пустой базовый слой для сверхлёгких образов.\"}]}]}]},{\"type\":\"horizontalRule\"},{\"type\":\"heading\",\"attrs\":{\"textAlign\":null,\"level\":3},\"content\":[{\"type\":\"text\",\"marks\":[{\"type\":\"bold\"}],\"text\":\"Зачем нужен базовый образ\"}]},{\"type\":\"bulletList\",\"content\":[{\"type\":\"listItem\",\"content\":[{\"type\":\"paragraph\",\"attrs\":{\"textAlign\":null},\"content\":[{\"type\":\"text\",\"text\":\"задаёт окружение и файловую систему для будущего контейнера;\"}]}]},{\"type\":\"listItem\",\"content\":[{\"type\":\"paragraph\",\"attrs\":{\"textAlign\":null},\"content\":[{\"type\":\"text\",\"text\":\"избавляет от необходимости настраивать всё с нуля;\"}]}]},{\"type\":\"listItem\",\"content\":[{\"type\":\"paragraph\",\"attrs\":{\"textAlign\":null},\"content\":[{\"type\":\"text\",\"text\":\"ускоряет сборку благодаря готовым слоям.\"}]}]}]},{\"type\":\"horizontalRule\"},{\"type\":\"paragraph\",\"attrs\":{\"textAlign\":null},\"content\":[{\"type\":\"text\",\"marks\":[{\"type\":\"bold\"}],\"text\":\"Коротко:\"},{\"type\":\"text\",\"text\":\" базовый образ — это фундамент, на который в Dockerfile «надстраиваются» остальные слои образа.\"}]}]}",
        "grade": "trainee",
        "language": null,
        "generationSource": "USER",
        "framework": null,
        "expectedAnswer": null,
        "categoryId": 192,
        "createdAt": "2025-10-22T08:03:05.406Z",
        "updatedAt": "2025-11-10T13:17:12.781Z",
        "favoriteByUsers": [],
        "userProgress": [],
        "category": {
          "id": 192,
          "title": "Docker образы (images)",
          "directions": [
            {
              "categoryId": 192,
              "directionId": 5,
              "direction": {
                "id": 5,
                "title": "Инструменты и технологии",
                "order": 5,
                "isReady": true,
                "isVisible": true,
                "languages": [],
                "hasGrades": null,
                "frameworks": [],
                "createdAt": "2025-09-07T10:01:35.439Z",
                "updatedAt": "2025-11-26T11:09:24.423Z"
              }
            }
          ],
          "parent": {
            "title": "Docker",
            "id": 164,
            "parent": null
          }
        }
      },
      "previous": {
        "title": "Что такое Dockerfile?",
        "id": 1862,
        "premium": false,
        "category": {
          "id": 192,
          "parent": {
            "title": "Docker",
            "id": 164,
            "parent": null
          },
          "directions": [
            {
              "directionId": 5
            }
          ]
        }
      },
      "next": {
        "title": "Что такое multi-stage build?",
        "id": 1864,
        "premium": false,
        "category": {
          "id": 192,
          "parent": {
            "title": "Docker",
            "id": 164,
            "parent": null
          },
          "directions": [
            {
              "directionId": 5
            }
          ]
        }
      }
    },
    {
      "current": {
        "id": 1864,
        "type": "boolean",
        "text": "{\"type\":\"doc\",\"content\":[{\"type\":\"paragraph\",\"attrs\":{\"textAlign\":null},\"content\":[{\"type\":\"text\",\"text\":\"Что такое multi-stage build?\"}]}]}",
        "title": "Что такое multi-stage build?",
        "order": 500109,
        "premium": false,
        "isPopular": false,
        "explanation": "{\"type\":\"doc\",\"content\":[{\"type\":\"paragraph\",\"attrs\":{\"textAlign\":null},\"content\":[{\"type\":\"text\",\"text\":\"Multi-stage build — это способ сборки Docker-образа, при котором используется \"},{\"type\":\"text\",\"marks\":[{\"type\":\"bold\"}],\"text\":\"несколько стадий (слоёв сборки)\"},{\"type\":\"text\",\"text\":\" в одном Dockerfile, чтобы итоговый образ получился \"},{\"type\":\"text\",\"marks\":[{\"type\":\"bold\"}],\"text\":\"меньше и чище\"},{\"type\":\"text\",\"text\":\".\"}]},{\"type\":\"horizontalRule\"},{\"type\":\"heading\",\"attrs\":{\"textAlign\":null,\"level\":3},\"content\":[{\"type\":\"text\",\"marks\":[{\"type\":\"bold\"}],\"text\":\"Зачем это нужно (по-junior’ски)\"}]},{\"type\":\"paragraph\",\"attrs\":{\"textAlign\":null},\"content\":[{\"type\":\"text\",\"text\":\"Обычно для сборки приложения нужны компиляторы, dev-зависимости и инструменты. Но в финальном образе они \"},{\"type\":\"text\",\"marks\":[{\"type\":\"bold\"}],\"text\":\"не нужны\"},{\"type\":\"text\",\"text\":\" и только занимают место. Multi-stage build позволяет:\"}]},{\"type\":\"bulletList\",\"content\":[{\"type\":\"listItem\",\"content\":[{\"type\":\"paragraph\",\"attrs\":{\"textAlign\":null},\"content\":[{\"type\":\"text\",\"text\":\"собирать приложение в \"},{\"type\":\"text\",\"marks\":[{\"type\":\"bold\"}],\"text\":\"одной стадии\"},{\"type\":\"text\",\"text\":\",\"}]}]},{\"type\":\"listItem\",\"content\":[{\"type\":\"paragraph\",\"attrs\":{\"textAlign\":null},\"content\":[{\"type\":\"text\",\"text\":\"а в \"},{\"type\":\"text\",\"marks\":[{\"type\":\"bold\"}],\"text\":\"финальный образ копировать только результат\"},{\"type\":\"text\",\"text\":\" (например, бинарник или скомпилированный код).\"}]}]}]},{\"type\":\"horizontalRule\"},{\"type\":\"heading\",\"attrs\":{\"textAlign\":null,\"level\":3},\"content\":[{\"type\":\"text\",\"marks\":[{\"type\":\"bold\"}],\"text\":\"Как это выглядит\"}]},{\"type\":\"codeBlock\",\"attrs\":{\"language\":\"Dockerfile\"},\"content\":[{\"type\":\"text\",\"text\":\"# 1) стадия сборки\\nFROM golang:1.20 AS builder\\nWORKDIR /app\\nCOPY . .\\nRUN go build -o app\\n\\n# 2) финальная стадия\\nFROM alpine:latest\\nCOPY --from=builder /app/app /app/app\\nCMD [\\\"/app/app\\\"]\\n\"}]},{\"type\":\"horizontalRule\"},{\"type\":\"heading\",\"attrs\":{\"textAlign\":null,\"level\":3},\"content\":[{\"type\":\"text\",\"marks\":[{\"type\":\"bold\"}],\"text\":\"Что происходит\"}]},{\"type\":\"table\",\"content\":[{\"type\":\"tableRow\",\"content\":[{\"type\":\"tableHeader\",\"attrs\":{\"colspan\":1,\"rowspan\":1,\"colwidth\":null},\"content\":[{\"type\":\"paragraph\",\"attrs\":{\"textAlign\":null},\"content\":[{\"type\":\"text\",\"text\":\"Стадия\"}]}]},{\"type\":\"tableHeader\",\"attrs\":{\"colspan\":1,\"rowspan\":1,\"colwidth\":null},\"content\":[{\"type\":\"paragraph\",\"attrs\":{\"textAlign\":null},\"content\":[{\"type\":\"text\",\"text\":\"Что делает\"}]}]}]},{\"type\":\"tableRow\",\"content\":[{\"type\":\"tableCell\",\"attrs\":{\"colspan\":1,\"rowspan\":1,\"colwidth\":null},\"content\":[{\"type\":\"paragraph\",\"attrs\":{\"textAlign\":null},\"content\":[{\"type\":\"text\",\"marks\":[{\"type\":\"code\"}],\"text\":\"builder\"}]}]},{\"type\":\"tableCell\",\"attrs\":{\"colspan\":1,\"rowspan\":1,\"colwidth\":null},\"content\":[{\"type\":\"paragraph\",\"attrs\":{\"textAlign\":null},\"content\":[{\"type\":\"text\",\"text\":\"Собирает приложение, включает тяжёлые зависимости\"}]}]}]},{\"type\":\"tableRow\",\"content\":[{\"type\":\"tableCell\",\"attrs\":{\"colspan\":1,\"rowspan\":1,\"colwidth\":null},\"content\":[{\"type\":\"paragraph\",\"attrs\":{\"textAlign\":null},\"content\":[{\"type\":\"text\",\"marks\":[{\"type\":\"code\"}],\"text\":\"final\"}]}]},{\"type\":\"tableCell\",\"attrs\":{\"colspan\":1,\"rowspan\":1,\"colwidth\":null},\"content\":[{\"type\":\"paragraph\",\"attrs\":{\"textAlign\":null},\"content\":[{\"type\":\"text\",\"text\":\"Берёт только готовый файл и ничего лишнего\"}]}]}]}]},{\"type\":\"horizontalRule\"},{\"type\":\"heading\",\"attrs\":{\"textAlign\":null,\"level\":3},\"content\":[{\"type\":\"text\",\"marks\":[{\"type\":\"bold\"}],\"text\":\"Итог\"}]},{\"type\":\"bulletList\",\"content\":[{\"type\":\"listItem\",\"content\":[{\"type\":\"paragraph\",\"attrs\":{\"textAlign\":null},\"content\":[{\"type\":\"text\",\"text\":\"Итоговый образ \"},{\"type\":\"text\",\"marks\":[{\"type\":\"bold\"}],\"text\":\"маленький\"}]}]},{\"type\":\"listItem\",\"content\":[{\"type\":\"paragraph\",\"attrs\":{\"textAlign\":null},\"content\":[{\"type\":\"text\",\"text\":\"В нём \"},{\"type\":\"text\",\"marks\":[{\"type\":\"bold\"}],\"text\":\"только то, что нужно на проде\"}]}]},{\"type\":\"listItem\",\"content\":[{\"type\":\"paragraph\",\"attrs\":{\"textAlign\":null},\"content\":[{\"type\":\"text\",\"text\":\"Без dev-мусора, без компиляторов\"}]}]}]},{\"type\":\"horizontalRule\"},{\"type\":\"paragraph\",\"attrs\":{\"textAlign\":null},\"content\":[{\"type\":\"text\",\"marks\":[{\"type\":\"bold\"}],\"text\":\"В одной фразе:\"},{\"type\":\"text\",\"text\":\" Multi-stage build — это способ собрать приложение в одном образе, а запустить в другом, меньшем и чистом.\"}]}]}",
        "grade": "junior",
        "language": null,
        "generationSource": "USER",
        "framework": null,
        "expectedAnswer": null,
        "categoryId": 192,
        "createdAt": "2025-10-22T08:03:22.550Z",
        "updatedAt": "2025-10-22T08:03:22.550Z",
        "favoriteByUsers": [],
        "userProgress": [],
        "category": {
          "id": 192,
          "title": "Docker образы (images)",
          "directions": [
            {
              "categoryId": 192,
              "directionId": 5,
              "direction": {
                "id": 5,
                "title": "Инструменты и технологии",
                "order": 5,
                "isReady": true,
                "isVisible": true,
                "languages": [],
                "hasGrades": null,
                "frameworks": [],
                "createdAt": "2025-09-07T10:01:35.439Z",
                "updatedAt": "2025-11-26T11:09:24.423Z"
              }
            }
          ],
          "parent": {
            "title": "Docker",
            "id": 164,
            "parent": null
          }
        }
      },
      "previous": {
        "title": "Что такое базовый образ (base image)? ",
        "id": 1863,
        "premium": true,
        "category": {
          "id": 192,
          "parent": {
            "title": "Docker",
            "id": 164,
            "parent": null
          },
          "directions": [
            {
              "directionId": 5
            }
          ]
        }
      },
      "next": {
        "title": "Что делает AS builder в Dockerfile?",
        "id": 1865,
        "premium": false,
        "category": {
          "id": 192,
          "parent": {
            "title": "Docker",
            "id": 164,
            "parent": null
          },
          "directions": [
            {
              "directionId": 5
            }
          ]
        }
      }
    },
    {
      "current": {
        "id": 1865,
        "type": "boolean",
        "text": "{\"type\":\"doc\",\"content\":[{\"type\":\"paragraph\",\"attrs\":{\"textAlign\":null},\"content\":[{\"type\":\"text\",\"text\":\"Что делает \"},{\"type\":\"text\",\"marks\":[{\"type\":\"code\"}],\"text\":\"AS builder\"},{\"type\":\"text\",\"text\":\" в Dockerfile?\"}]}]}",
        "title": "Что делает AS builder в Dockerfile?",
        "order": 500110,
        "premium": false,
        "isPopular": false,
        "explanation": "{\"type\":\"doc\",\"content\":[{\"type\":\"paragraph\",\"attrs\":{\"textAlign\":null},\"content\":[{\"type\":\"text\",\"marks\":[{\"type\":\"code\"}],\"text\":\"AS builder\"},{\"type\":\"text\",\"text\":\" — это имя (alias), которое присваивается конкретной стадии сборки в \"},{\"type\":\"text\",\"marks\":[{\"type\":\"bold\"}],\"text\":\"multi-stage build\"},{\"type\":\"text\",\"text\":\". Это просто метка, чтобы потом можно было ссылаться на эту стадию в следующих этапах.\"}]},{\"type\":\"horizontalRule\"},{\"type\":\"heading\",\"attrs\":{\"textAlign\":null,\"level\":3},\"content\":[{\"type\":\"text\",\"marks\":[{\"type\":\"bold\"}],\"text\":\"Как это работает\"}]},{\"type\":\"codeBlock\",\"attrs\":{\"language\":\"Dockerfile\"},\"content\":[{\"type\":\"text\",\"text\":\"FROM golang:1.20 AS builder\\n\"}]},{\"type\":\"paragraph\",\"attrs\":{\"textAlign\":null},\"content\":[{\"type\":\"text\",\"text\":\"Здесь \"},{\"type\":\"text\",\"marks\":[{\"type\":\"code\"}],\"text\":\"builder\"},{\"type\":\"text\",\"text\":\" — имя стадии. Далее можно в финальном образе обратиться к результатам этой стадии:\"}]},{\"type\":\"codeBlock\",\"attrs\":{\"language\":\"Dockerfile\"},\"content\":[{\"type\":\"text\",\"text\":\"COPY --from=builder /app/app /app/app\\n\"}]},{\"type\":\"horizontalRule\"},{\"type\":\"heading\",\"attrs\":{\"textAlign\":null,\"level\":3},\"content\":[{\"type\":\"text\",\"marks\":[{\"type\":\"bold\"}],\"text\":\"Зачем это нужно\"}]},{\"type\":\"orderedList\",\"attrs\":{\"start\":1,\"type\":null},\"content\":[{\"type\":\"listItem\",\"content\":[{\"type\":\"paragraph\",\"attrs\":{\"textAlign\":null},\"content\":[{\"type\":\"text\",\"marks\":[{\"type\":\"bold\"}],\"text\":\"Удобно ссылаться на нужную стадию\"},{\"type\":\"hardBreak\"},{\"type\":\"text\",\"text\":\"Можно иметь несколько стадий — \"},{\"type\":\"text\",\"marks\":[{\"type\":\"code\"}],\"text\":\"builder\"},{\"type\":\"text\",\"text\":\", \"},{\"type\":\"text\",\"marks\":[{\"type\":\"code\"}],\"text\":\"test\"},{\"type\":\"text\",\"text\":\", \"},{\"type\":\"text\",\"marks\":[{\"type\":\"code\"}],\"text\":\"final\"},{\"type\":\"text\",\"text\":\" и копировать файлы из любой.\"}]}]},{\"type\":\"listItem\",\"content\":[{\"type\":\"paragraph\",\"attrs\":{\"textAlign\":null},\"content\":[{\"type\":\"text\",\"marks\":[{\"type\":\"bold\"}],\"text\":\"Улучшает читаемость\"},{\"type\":\"hardBreak\"},{\"type\":\"text\",\"text\":\"Понятно, какая стадия для чего.\"}]}]},{\"type\":\"listItem\",\"content\":[{\"type\":\"paragraph\",\"attrs\":{\"textAlign\":null},\"content\":[{\"type\":\"text\",\"marks\":[{\"type\":\"bold\"}],\"text\":\"Нужно для multi-stage build\"},{\"type\":\"hardBreak\"},{\"type\":\"text\",\"text\":\"Без имени пришлось бы указывать номер стадии (менее удобно).\"}]}]}]},{\"type\":\"horizontalRule\"},{\"type\":\"heading\",\"attrs\":{\"textAlign\":null,\"level\":3},\"content\":[{\"type\":\"text\",\"marks\":[{\"type\":\"bold\"}],\"text\":\"Если в одну фразу (junior)\"}]},{\"type\":\"paragraph\",\"attrs\":{\"textAlign\":null},\"content\":[{\"type\":\"text\",\"marks\":[{\"type\":\"code\"}],\"text\":\"AS builder\"},{\"type\":\"text\",\"text\":\" даёт название стадии сборки, чтобы в других этапах Dockerfile можно было взять из неё файлы или артефакты.\"}]}]}",
        "grade": "junior",
        "language": null,
        "generationSource": "USER",
        "framework": null,
        "expectedAnswer": null,
        "categoryId": 192,
        "createdAt": "2025-10-22T08:03:38.080Z",
        "updatedAt": "2025-10-22T08:03:38.080Z",
        "favoriteByUsers": [],
        "userProgress": [],
        "category": {
          "id": 192,
          "title": "Docker образы (images)",
          "directions": [
            {
              "categoryId": 192,
              "directionId": 5,
              "direction": {
                "id": 5,
                "title": "Инструменты и технологии",
                "order": 5,
                "isReady": true,
                "isVisible": true,
                "languages": [],
                "hasGrades": null,
                "frameworks": [],
                "createdAt": "2025-09-07T10:01:35.439Z",
                "updatedAt": "2025-11-26T11:09:24.423Z"
              }
            }
          ],
          "parent": {
            "title": "Docker",
            "id": 164,
            "parent": null
          }
        }
      },
      "previous": {
        "title": "Что такое multi-stage build?",
        "id": 1864,
        "premium": false,
        "category": {
          "id": 192,
          "parent": {
            "title": "Docker",
            "id": 164,
            "parent": null
          },
          "directions": [
            {
              "directionId": 5
            }
          ]
        }
      },
      "next": {
        "title": "Как Docker объединяет слои в образе?",
        "id": 1866,
        "premium": true,
        "category": {
          "id": 192,
          "parent": {
            "title": "Docker",
            "id": 164,
            "parent": null
          },
          "directions": [
            {
              "directionId": 5
            }
          ]
        }
      }
    },
    {
      "current": {
        "id": 1866,
        "type": "boolean",
        "text": "{\"type\":\"doc\",\"content\":[{\"type\":\"paragraph\",\"attrs\":{\"textAlign\":null},\"content\":[{\"type\":\"text\",\"text\":\"Как Docker объединяет слои в образе?\"}]}]}",
        "title": "Как Docker объединяет слои в образе?",
        "order": 500111,
        "premium": true,
        "isPopular": false,
        "explanation": "{\"type\":\"doc\",\"content\":[{\"type\":\"paragraph\",\"attrs\":{\"textAlign\":null},\"content\":[{\"type\":\"text\",\"text\":\"Docker объединяет слои с помощью механизмов \"},{\"type\":\"text\",\"marks\":[{\"type\":\"bold\"}],\"text\":\"union filesystem (OverlayFS, AUFS и др.)\"},{\"type\":\"text\",\"text\":\". Каждый слой — это отдельный read-only кусок файловой системы, а при сборке образа эти слои \"},{\"type\":\"text\",\"marks\":[{\"type\":\"bold\"}],\"text\":\"логически “наслаиваются” друг на друга\"},{\"type\":\"text\",\"text\":\", образуя единый видимый root-fs для контейнера.\"}]},{\"type\":\"horizontalRule\"},{\"type\":\"heading\",\"attrs\":{\"textAlign\":null,\"level\":3},\"content\":[{\"type\":\"text\",\"marks\":[{\"type\":\"bold\"}],\"text\":\"Как это работает по шагам\"}]},{\"type\":\"orderedList\",\"attrs\":{\"start\":1,\"type\":null},\"content\":[{\"type\":\"listItem\",\"content\":[{\"type\":\"paragraph\",\"attrs\":{\"textAlign\":null},\"content\":[{\"type\":\"text\",\"marks\":[{\"type\":\"bold\"}],\"text\":\"Каждая инструкция Dockerfile создаёт слой\"},{\"type\":\"hardBreak\"},{\"type\":\"text\",\"marks\":[{\"type\":\"code\"}],\"text\":\"FROM\"},{\"type\":\"text\",\"text\":\", \"},{\"type\":\"text\",\"marks\":[{\"type\":\"code\"}],\"text\":\"RUN\"},{\"type\":\"text\",\"text\":\", \"},{\"type\":\"text\",\"marks\":[{\"type\":\"code\"}],\"text\":\"COPY\"},{\"type\":\"text\",\"text\":\" и др. → новый слой (read-only).\"}]}]},{\"type\":\"listItem\",\"content\":[{\"type\":\"paragraph\",\"attrs\":{\"textAlign\":null},\"content\":[{\"type\":\"text\",\"marks\":[{\"type\":\"bold\"}],\"text\":\"Слои не сливаются физически\"},{\"type\":\"hardBreak\"},{\"type\":\"text\",\"text\":\"Docker не копирует содержимое каждого слоя внутрь следующего. Вместо этого он использует union-mount, который делает их \"},{\"type\":\"text\",\"marks\":[{\"type\":\"bold\"}],\"text\":\"единым деревом каталогов\"},{\"type\":\"text\",\"text\":\".\"}]}]},{\"type\":\"listItem\",\"content\":[{\"type\":\"paragraph\",\"attrs\":{\"textAlign\":null},\"content\":[{\"type\":\"text\",\"marks\":[{\"type\":\"bold\"}],\"text\":\"OverlayFS объединяет их через механизмы \"},{\"type\":\"text\",\"marks\":[{\"type\":\"code\"}],\"text\":\"lowerdir/upperdir\"},{\"type\":\"hardBreak\"},{\"type\":\"text\",\"text\":\"Основная схема:\"}]},{\"type\":\"table\",\"content\":[{\"type\":\"tableRow\",\"content\":[{\"type\":\"tableHeader\",\"attrs\":{\"colspan\":1,\"rowspan\":1,\"colwidth\":null},\"content\":[{\"type\":\"paragraph\",\"attrs\":{\"textAlign\":null},\"content\":[{\"type\":\"text\",\"text\":\"Компонент\"}]}]},{\"type\":\"tableHeader\",\"attrs\":{\"colspan\":1,\"rowspan\":1,\"colwidth\":null},\"content\":[{\"type\":\"paragraph\",\"attrs\":{\"textAlign\":null},\"content\":[{\"type\":\"text\",\"text\":\"Что это\"}]}]}]},{\"type\":\"tableRow\",\"content\":[{\"type\":\"tableCell\",\"attrs\":{\"colspan\":1,\"rowspan\":1,\"colwidth\":null},\"content\":[{\"type\":\"paragraph\",\"attrs\":{\"textAlign\":null},\"content\":[{\"type\":\"text\",\"marks\":[{\"type\":\"code\"}],\"text\":\"lowerdir\"}]}]},{\"type\":\"tableCell\",\"attrs\":{\"colspan\":1,\"rowspan\":1,\"colwidth\":null},\"content\":[{\"type\":\"paragraph\",\"attrs\":{\"textAlign\":null},\"content\":[{\"type\":\"text\",\"text\":\"слои образа (read-only, один над другим)\"}]}]}]},{\"type\":\"tableRow\",\"content\":[{\"type\":\"tableCell\",\"attrs\":{\"colspan\":1,\"rowspan\":1,\"colwidth\":null},\"content\":[{\"type\":\"paragraph\",\"attrs\":{\"textAlign\":null},\"content\":[{\"type\":\"text\",\"marks\":[{\"type\":\"code\"}],\"text\":\"upperdir\"}]}]},{\"type\":\"tableCell\",\"attrs\":{\"colspan\":1,\"rowspan\":1,\"colwidth\":null},\"content\":[{\"type\":\"paragraph\",\"attrs\":{\"textAlign\":null},\"content\":[{\"type\":\"text\",\"text\":\"слой с изменениями (при работе контейнера)\"}]}]}]},{\"type\":\"tableRow\",\"content\":[{\"type\":\"tableCell\",\"attrs\":{\"colspan\":1,\"rowspan\":1,\"colwidth\":null},\"content\":[{\"type\":\"paragraph\",\"attrs\":{\"textAlign\":null},\"content\":[{\"type\":\"text\",\"marks\":[{\"type\":\"code\"}],\"text\":\"merged\"}]}]},{\"type\":\"tableCell\",\"attrs\":{\"colspan\":1,\"rowspan\":1,\"colwidth\":null},\"content\":[{\"type\":\"paragraph\",\"attrs\":{\"textAlign\":null},\"content\":[{\"type\":\"text\",\"text\":\"итоговая, смонтированная файловая система\"}]}]}]}]}]},{\"type\":\"listItem\",\"content\":[{\"type\":\"paragraph\",\"attrs\":{\"textAlign\":null},\"content\":[{\"type\":\"text\",\"marks\":[{\"type\":\"bold\"}],\"text\":\"Когда файл меняется — CoW (copy-on-write)\"},{\"type\":\"hardBreak\"},{\"type\":\"text\",\"text\":\"Если контейнер изменяет файл из нижнего слоя, Docker \"},{\"type\":\"text\",\"marks\":[{\"type\":\"bold\"}],\"text\":\"копирует его в верхний слой\"},{\"type\":\"text\",\"text\":\" и правка происходит уже там, не трогая базовые слои.\"}]}]}]},{\"type\":\"horizontalRule\"},{\"type\":\"heading\",\"attrs\":{\"textAlign\":null,\"level\":3},\"content\":[{\"type\":\"text\",\"marks\":[{\"type\":\"bold\"}],\"text\":\"Что это даёт\"}]},{\"type\":\"table\",\"content\":[{\"type\":\"tableRow\",\"content\":[{\"type\":\"tableHeader\",\"attrs\":{\"colspan\":1,\"rowspan\":1,\"colwidth\":null},\"content\":[{\"type\":\"paragraph\",\"attrs\":{\"textAlign\":null},\"content\":[{\"type\":\"text\",\"text\":\"Преимущество\"}]}]},{\"type\":\"tableHeader\",\"attrs\":{\"colspan\":1,\"rowspan\":1,\"colwidth\":null},\"content\":[{\"type\":\"paragraph\",\"attrs\":{\"textAlign\":null},\"content\":[{\"type\":\"text\",\"text\":\"За счёт чего\"}]}]}]},{\"type\":\"tableRow\",\"content\":[{\"type\":\"tableCell\",\"attrs\":{\"colspan\":1,\"rowspan\":1,\"colwidth\":null},\"content\":[{\"type\":\"paragraph\",\"attrs\":{\"textAlign\":null},\"content\":[{\"type\":\"text\",\"text\":\"Экономия места\"}]}]},{\"type\":\"tableCell\",\"attrs\":{\"colspan\":1,\"rowspan\":1,\"colwidth\":null},\"content\":[{\"type\":\"paragraph\",\"attrs\":{\"textAlign\":null},\"content\":[{\"type\":\"text\",\"text\":\"слои переиспользуются разными образами\"}]}]}]},{\"type\":\"tableRow\",\"content\":[{\"type\":\"tableCell\",\"attrs\":{\"colspan\":1,\"rowspan\":1,\"colwidth\":null},\"content\":[{\"type\":\"paragraph\",\"attrs\":{\"textAlign\":null},\"content\":[{\"type\":\"text\",\"text\":\"Быстрая сборка\"}]}]},{\"type\":\"tableCell\",\"attrs\":{\"colspan\":1,\"rowspan\":1,\"colwidth\":null},\"content\":[{\"type\":\"paragraph\",\"attrs\":{\"textAlign\":null},\"content\":[{\"type\":\"text\",\"text\":\"кэш слоёв, не пересобираются ранее созданные\"}]}]}]},{\"type\":\"tableRow\",\"content\":[{\"type\":\"tableCell\",\"attrs\":{\"colspan\":1,\"rowspan\":1,\"colwidth\":null},\"content\":[{\"type\":\"paragraph\",\"attrs\":{\"textAlign\":null},\"content\":[{\"type\":\"text\",\"text\":\"Иммутабельность\"}]}]},{\"type\":\"tableCell\",\"attrs\":{\"colspan\":1,\"rowspan\":1,\"colwidth\":null},\"content\":[{\"type\":\"paragraph\",\"attrs\":{\"textAlign\":null},\"content\":[{\"type\":\"text\",\"text\":\"нижние слои read-only, не портятся\"}]}]}]}]},{\"type\":\"horizontalRule\"},{\"type\":\"heading\",\"attrs\":{\"textAlign\":null,\"level\":3},\"content\":[{\"type\":\"text\",\"marks\":[{\"type\":\"bold\"}],\"text\":\"Главная мысль для middle-уровня\"}]},{\"type\":\"blockquote\",\"content\":[{\"type\":\"paragraph\",\"attrs\":{\"textAlign\":null},\"content\":[{\"type\":\"text\",\"text\":\"Docker не «склеивает» слои в один физический слой. Он \"},{\"type\":\"text\",\"marks\":[{\"type\":\"bold\"}],\"text\":\"монтирует их поверх друг друга с помощью OverlayFS\"},{\"type\":\"text\",\"text\":\", а изменения в контейнере происходят только в верхнем writable-слое, используя CoW.\"}]}]},{\"type\":\"horizontalRule\"},{\"type\":\"paragraph\",\"attrs\":{\"textAlign\":null},\"content\":[{\"type\":\"text\",\"text\":\"Если хочешь, могу дополнить разницей \"},{\"type\":\"text\",\"marks\":[{\"type\":\"bold\"}],\"text\":\"между OverlayFS и AUFS\"},{\"type\":\"text\",\"text\":\" или разобрать этот же процесс на уровне системных директорий (\"},{\"type\":\"text\",\"marks\":[{\"type\":\"code\"}],\"text\":\"/var/lib/docker/overlay2\"},{\"type\":\"text\",\"text\":\").\"}]}]}",
        "grade": "middle",
        "language": null,
        "generationSource": "USER",
        "framework": null,
        "expectedAnswer": null,
        "categoryId": 192,
        "createdAt": "2025-10-22T08:03:57.116Z",
        "updatedAt": "2025-11-10T13:17:16.618Z",
        "favoriteByUsers": [],
        "userProgress": [],
        "category": {
          "id": 192,
          "title": "Docker образы (images)",
          "directions": [
            {
              "categoryId": 192,
              "directionId": 5,
              "direction": {
                "id": 5,
                "title": "Инструменты и технологии",
                "order": 5,
                "isReady": true,
                "isVisible": true,
                "languages": [],
                "hasGrades": null,
                "frameworks": [],
                "createdAt": "2025-09-07T10:01:35.439Z",
                "updatedAt": "2025-11-26T11:09:24.423Z"
              }
            }
          ],
          "parent": {
            "title": "Docker",
            "id": 164,
            "parent": null
          }
        }
      },
      "previous": {
        "title": "Что делает AS builder в Dockerfile?",
        "id": 1865,
        "premium": false,
        "category": {
          "id": 192,
          "parent": {
            "title": "Docker",
            "id": 164,
            "parent": null
          },
          "directions": [
            {
              "directionId": 5
            }
          ]
        }
      },
      "next": {
        "title": "Что такое контейнер в Docker? ",
        "id": 1867,
        "premium": false,
        "category": {
          "id": 193,
          "parent": {
            "title": "Docker",
            "id": 164,
            "parent": null
          },
          "directions": [
            {
              "directionId": 5
            }
          ]
        }
      }
    }
  ]
}