{
  "category": {
    "id": 136,
    "title": "Очередь и Дек (Queue)",
    "description": " ",
    "parentId": 11
  },
  "totalQuestions": 14,
  "downloadedAt": "2026-03-10T09:40:06.666Z",
  "questions": [
    {
      "current": {
        "id": 1550,
        "type": "boolean",
        "text": "{\"type\":\"doc\",\"content\":[{\"type\":\"paragraph\",\"attrs\":{\"textAlign\":null},\"content\":[{\"type\":\"text\",\"text\":\"Что такое очередь?\"}]}]}",
        "title": "Что такое очередь?",
        "order": 410500,
        "premium": false,
        "isPopular": false,
        "explanation": "{\"type\":\"doc\",\"content\":[{\"type\":\"paragraph\",\"attrs\":{\"textAlign\":null},\"content\":[{\"type\":\"text\",\"marks\":[{\"type\":\"bold\"}],\"text\":\"Очередь\"},{\"type\":\"text\",\"text\":\" — это структура данных, работающая по принципу \"},{\"type\":\"text\",\"marks\":[{\"type\":\"bold\"}],\"text\":\"FIFO (First In, First Out)\"},{\"type\":\"text\",\"text\":\" — \"},{\"type\":\"text\",\"marks\":[{\"type\":\"italic\"}],\"text\":\"первым пришёл, первым ушёл\"},{\"type\":\"text\",\"text\":\".\"}]},{\"type\":\"paragraph\",\"attrs\":{\"textAlign\":null},\"content\":[{\"type\":\"text\",\"text\":\"То есть элемент, добавленный первым, будет извлечён раньше остальных.\"}]},{\"type\":\"paragraph\",\"attrs\":{\"textAlign\":null},\"content\":[{\"type\":\"text\",\"text\":\"Основные операции очереди:\"}]},{\"type\":\"bulletList\",\"content\":[{\"type\":\"listItem\",\"content\":[{\"type\":\"paragraph\",\"attrs\":{\"textAlign\":null},\"content\":[{\"type\":\"text\",\"marks\":[{\"type\":\"bold\"}],\"text\":\"enqueue(x)\"},{\"type\":\"text\",\"text\":\" — добавить элемент \"},{\"type\":\"text\",\"marks\":[{\"type\":\"code\"}],\"text\":\"x\"},{\"type\":\"text\",\"text\":\" в конец очереди,\"}]}]},{\"type\":\"listItem\",\"content\":[{\"type\":\"paragraph\",\"attrs\":{\"textAlign\":null},\"content\":[{\"type\":\"text\",\"marks\":[{\"type\":\"bold\"}],\"text\":\"dequeue()\"},{\"type\":\"text\",\"text\":\" — удалить и вернуть элемент из начала очереди,\"}]}]},{\"type\":\"listItem\",\"content\":[{\"type\":\"paragraph\",\"attrs\":{\"textAlign\":null},\"content\":[{\"type\":\"text\",\"marks\":[{\"type\":\"bold\"}],\"text\":\"peek() / front()\"},{\"type\":\"text\",\"text\":\" — посмотреть элемент в начале без удаления,\"}]}]},{\"type\":\"listItem\",\"content\":[{\"type\":\"paragraph\",\"attrs\":{\"textAlign\":null},\"content\":[{\"type\":\"text\",\"marks\":[{\"type\":\"bold\"}],\"text\":\"isEmpty()\"},{\"type\":\"text\",\"text\":\" — проверить, пуста ли очередь.\"}]}]}]},{\"type\":\"paragraph\",\"attrs\":{\"textAlign\":null},\"content\":[{\"type\":\"text\",\"text\":\"Пример: очередь людей в магазине — кто первый встал, тот первый обслуживается.\"}]},{\"type\":\"paragraph\",\"attrs\":{\"textAlign\":null},\"content\":[{\"type\":\"text\",\"text\":\"Очередь часто используется:\"}]},{\"type\":\"bulletList\",\"content\":[{\"type\":\"listItem\",\"content\":[{\"type\":\"paragraph\",\"attrs\":{\"textAlign\":null},\"content\":[{\"type\":\"text\",\"text\":\"при планировании задач (процессы, потоки, принтеры),\"}]}]},{\"type\":\"listItem\",\"content\":[{\"type\":\"paragraph\",\"attrs\":{\"textAlign\":null},\"content\":[{\"type\":\"text\",\"text\":\"в сетях (обработка пакетов),\"}]}]},{\"type\":\"listItem\",\"content\":[{\"type\":\"paragraph\",\"attrs\":{\"textAlign\":null},\"content\":[{\"type\":\"text\",\"text\":\"при обходе графов в ширину (\"},{\"type\":\"text\",\"marks\":[{\"type\":\"bold\"}],\"text\":\"BFS\"},{\"type\":\"text\",\"text\":\"),\"}]}]},{\"type\":\"listItem\",\"content\":[{\"type\":\"paragraph\",\"attrs\":{\"textAlign\":null},\"content\":[{\"type\":\"text\",\"text\":\"в асинхронных системах (очереди сообщений, событий).\"}]}]}]},{\"type\":\"paragraph\",\"attrs\":{\"textAlign\":null}}]}",
        "grade": "trainee",
        "language": null,
        "generationSource": "USER",
        "framework": null,
        "expectedAnswer": null,
        "categoryId": 136,
        "createdAt": "2025-10-21T08:16:49.498Z",
        "updatedAt": "2025-10-21T08:16:49.498Z",
        "favoriteByUsers": [],
        "userProgress": [],
        "category": {
          "id": 136,
          "title": "Очередь и Дек (Queue)",
          "directions": [
            {
              "categoryId": 136,
              "directionId": 3,
              "direction": {
                "id": 3,
                "title": "Computer science",
                "order": 3,
                "isReady": true,
                "isVisible": true,
                "languages": [],
                "hasGrades": null,
                "frameworks": [],
                "createdAt": "2025-09-07T10:01:17.530Z",
                "updatedAt": "2025-11-26T11:08:54.386Z"
              }
            }
          ],
          "parent": {
            "title": "Структуры данных",
            "id": 11,
            "parent": null
          }
        }
      },
      "previous": {
        "title": "В каких задачах чаще всего используется стек?",
        "id": 1549,
        "premium": false,
        "category": {
          "id": 135,
          "parent": {
            "title": "Структуры данных",
            "id": 11,
            "parent": null
          },
          "directions": [
            {
              "directionId": 3
            }
          ]
        }
      },
      "next": {
        "title": "Какой принцип лежит в основе работы очереди?",
        "id": 1551,
        "premium": false,
        "category": {
          "id": 136,
          "parent": {
            "title": "Структуры данных",
            "id": 11,
            "parent": null
          },
          "directions": [
            {
              "directionId": 3
            }
          ]
        }
      }
    },
    {
      "current": {
        "id": 1551,
        "type": "boolean",
        "text": "{\"type\":\"doc\",\"content\":[{\"type\":\"paragraph\",\"attrs\":{\"textAlign\":null},\"content\":[{\"type\":\"text\",\"text\":\"Какой принцип лежит в основе работы очереди?\"}]}]}",
        "title": "Какой принцип лежит в основе работы очереди?",
        "order": 410501,
        "premium": false,
        "isPopular": false,
        "explanation": "{\"type\":\"doc\",\"content\":[{\"type\":\"paragraph\",\"attrs\":{\"textAlign\":null},\"content\":[{\"type\":\"text\",\"text\":\"В основе работы очереди лежит принцип \"},{\"type\":\"text\",\"marks\":[{\"type\":\"bold\"}],\"text\":\"FIFO (First In, First Out)\"},{\"type\":\"text\",\"text\":\" — \"},{\"type\":\"text\",\"marks\":[{\"type\":\"italic\"}],\"text\":\"первым пришёл, первым ушёл\"},{\"type\":\"text\",\"text\":\".\"}]},{\"type\":\"paragraph\",\"attrs\":{\"textAlign\":null},\"content\":[{\"type\":\"text\",\"text\":\"Это значит:\"}]},{\"type\":\"bulletList\",\"content\":[{\"type\":\"listItem\",\"content\":[{\"type\":\"paragraph\",\"attrs\":{\"textAlign\":null},\"content\":[{\"type\":\"text\",\"text\":\"элементы добавляются \"},{\"type\":\"text\",\"marks\":[{\"type\":\"bold\"}],\"text\":\"в конец\"},{\"type\":\"text\",\"text\":\" очереди,\"}]}]},{\"type\":\"listItem\",\"content\":[{\"type\":\"paragraph\",\"attrs\":{\"textAlign\":null},\"content\":[{\"type\":\"text\",\"text\":\"извлекаются \"},{\"type\":\"text\",\"marks\":[{\"type\":\"bold\"}],\"text\":\"с начала\"},{\"type\":\"text\",\"text\":\",\"}]}]},{\"type\":\"listItem\",\"content\":[{\"type\":\"paragraph\",\"attrs\":{\"textAlign\":null},\"content\":[{\"type\":\"text\",\"text\":\"порядок обработки полностью соответствует порядку поступления.\"}]}]}]},{\"type\":\"paragraph\",\"attrs\":{\"textAlign\":null},\"content\":[{\"type\":\"text\",\"text\":\"Пример:\"},{\"type\":\"hardBreak\"},{\"type\":\"text\",\"text\":\"если в очередь поочерёдно добавить \"},{\"type\":\"text\",\"marks\":[{\"type\":\"code\"}],\"text\":\"1\"},{\"type\":\"text\",\"text\":\", \"},{\"type\":\"text\",\"marks\":[{\"type\":\"code\"}],\"text\":\"2\"},{\"type\":\"text\",\"text\":\", \"},{\"type\":\"text\",\"marks\":[{\"type\":\"code\"}],\"text\":\"3\"},{\"type\":\"text\",\"text\":\",\"},{\"type\":\"hardBreak\"},{\"type\":\"text\",\"text\":\"то при извлечении они выйдут в том же порядке — \"},{\"type\":\"text\",\"marks\":[{\"type\":\"code\"}],\"text\":\"1\"},{\"type\":\"text\",\"text\":\", \"},{\"type\":\"text\",\"marks\":[{\"type\":\"code\"}],\"text\":\"2\"},{\"type\":\"text\",\"text\":\", \"},{\"type\":\"text\",\"marks\":[{\"type\":\"code\"}],\"text\":\"3\"},{\"type\":\"text\",\"text\":\".\"}]},{\"type\":\"paragraph\",\"attrs\":{\"textAlign\":null},\"content\":[{\"type\":\"text\",\"text\":\"Таким образом, очередь моделирует \"},{\"type\":\"text\",\"marks\":[{\"type\":\"bold\"}],\"text\":\"естественный порядок ожидания\"},{\"type\":\"text\",\"text\":\" — как линия людей в кассу.\"}]}]}",
        "grade": "trainee",
        "language": null,
        "generationSource": "USER",
        "framework": null,
        "expectedAnswer": null,
        "categoryId": 136,
        "createdAt": "2025-10-21T08:17:05.843Z",
        "updatedAt": "2025-10-21T08:17:05.843Z",
        "favoriteByUsers": [],
        "userProgress": [],
        "category": {
          "id": 136,
          "title": "Очередь и Дек (Queue)",
          "directions": [
            {
              "categoryId": 136,
              "directionId": 3,
              "direction": {
                "id": 3,
                "title": "Computer science",
                "order": 3,
                "isReady": true,
                "isVisible": true,
                "languages": [],
                "hasGrades": null,
                "frameworks": [],
                "createdAt": "2025-09-07T10:01:17.530Z",
                "updatedAt": "2025-11-26T11:08:54.386Z"
              }
            }
          ],
          "parent": {
            "title": "Структуры данных",
            "id": 11,
            "parent": null
          }
        }
      },
      "previous": {
        "title": "Что такое очередь?",
        "id": 1550,
        "premium": false,
        "category": {
          "id": 136,
          "parent": {
            "title": "Структуры данных",
            "id": 11,
            "parent": null
          },
          "directions": [
            {
              "directionId": 3
            }
          ]
        }
      },
      "next": {
        "title": "Что означает “FIFO”?",
        "id": 1552,
        "premium": true,
        "category": {
          "id": 136,
          "parent": {
            "title": "Структуры данных",
            "id": 11,
            "parent": null
          },
          "directions": [
            {
              "directionId": 3
            }
          ]
        }
      }
    },
    {
      "current": {
        "id": 1552,
        "type": "boolean",
        "text": "{\"type\":\"doc\",\"content\":[{\"type\":\"paragraph\",\"attrs\":{\"textAlign\":null},\"content\":[{\"type\":\"text\",\"text\":\"Что означает “FIFO”?\"}]}]}",
        "title": "Что означает “FIFO”?",
        "order": 410502,
        "premium": true,
        "isPopular": false,
        "explanation": "{\"type\":\"doc\",\"content\":[{\"type\":\"paragraph\",\"attrs\":{\"textAlign\":null},\"content\":[{\"type\":\"text\",\"marks\":[{\"type\":\"bold\"}],\"text\":\"FIFO\"},{\"type\":\"text\",\"text\":\" расшифровывается как \"},{\"type\":\"text\",\"marks\":[{\"type\":\"bold\"}],\"text\":\"First In, First Out\"},{\"type\":\"text\",\"text\":\" — \"},{\"type\":\"text\",\"marks\":[{\"type\":\"italic\"}],\"text\":\"первым вошёл, первым вышел\"},{\"type\":\"text\",\"text\":\".\"}]},{\"type\":\"paragraph\",\"attrs\":{\"textAlign\":null},\"content\":[{\"type\":\"text\",\"text\":\"Это принцип, при котором элементы обрабатываются \"},{\"type\":\"text\",\"marks\":[{\"type\":\"bold\"}],\"text\":\"в том же порядке\"},{\"type\":\"text\",\"text\":\", в каком они были добавлены.\"},{\"type\":\"hardBreak\"},{\"type\":\"text\",\"text\":\"То есть первый добавленный элемент покидает структуру данных раньше всех остальных.\"}]},{\"type\":\"paragraph\",\"attrs\":{\"textAlign\":null},\"content\":[{\"type\":\"text\",\"text\":\"Пример:\"},{\"type\":\"hardBreak\"},{\"type\":\"text\",\"text\":\"Очередь в супермаркете — кто первый встал, тот первый обслужен.\"}]}]}",
        "grade": "trainee",
        "language": null,
        "generationSource": "USER",
        "framework": null,
        "expectedAnswer": null,
        "categoryId": 136,
        "createdAt": "2025-10-21T08:17:18.321Z",
        "updatedAt": "2025-11-10T13:12:25.318Z",
        "favoriteByUsers": [],
        "userProgress": [],
        "category": {
          "id": 136,
          "title": "Очередь и Дек (Queue)",
          "directions": [
            {
              "categoryId": 136,
              "directionId": 3,
              "direction": {
                "id": 3,
                "title": "Computer science",
                "order": 3,
                "isReady": true,
                "isVisible": true,
                "languages": [],
                "hasGrades": null,
                "frameworks": [],
                "createdAt": "2025-09-07T10:01:17.530Z",
                "updatedAt": "2025-11-26T11:08:54.386Z"
              }
            }
          ],
          "parent": {
            "title": "Структуры данных",
            "id": 11,
            "parent": null
          }
        }
      },
      "previous": {
        "title": "Какой принцип лежит в основе работы очереди?",
        "id": 1551,
        "premium": false,
        "category": {
          "id": 136,
          "parent": {
            "title": "Структуры данных",
            "id": 11,
            "parent": null
          },
          "directions": [
            {
              "directionId": 3
            }
          ]
        }
      },
      "next": {
        "title": "Чем очередь отличается от стека?",
        "id": 1553,
        "premium": true,
        "category": {
          "id": 136,
          "parent": {
            "title": "Структуры данных",
            "id": 11,
            "parent": null
          },
          "directions": [
            {
              "directionId": 3
            }
          ]
        }
      }
    },
    {
      "current": {
        "id": 1553,
        "type": "boolean",
        "text": "{\"type\":\"doc\",\"content\":[{\"type\":\"paragraph\",\"attrs\":{\"textAlign\":null},\"content\":[{\"type\":\"text\",\"text\":\"Чем очередь отличается от стека?\"}]}]}",
        "title": "Чем очередь отличается от стека?",
        "order": 410503,
        "premium": true,
        "isPopular": false,
        "explanation": "{\"type\":\"doc\",\"content\":[{\"type\":\"paragraph\",\"attrs\":{\"textAlign\":null},\"content\":[{\"type\":\"text\",\"text\":\"Очередь и стек отличаются \"},{\"type\":\"text\",\"marks\":[{\"type\":\"bold\"}],\"text\":\"порядком обработки элементов\"},{\"type\":\"text\",\"text\":\":\"}]},{\"type\":\"bulletList\",\"content\":[{\"type\":\"listItem\",\"content\":[{\"type\":\"paragraph\",\"attrs\":{\"textAlign\":null},\"content\":[{\"type\":\"text\",\"marks\":[{\"type\":\"bold\"}],\"text\":\"Стек\"},{\"type\":\"text\",\"text\":\" — принцип \"},{\"type\":\"text\",\"marks\":[{\"type\":\"bold\"}],\"text\":\"LIFO (Last In, First Out)\"},{\"type\":\"text\",\"text\":\": последним добавил — первым достал.\"},{\"type\":\"hardBreak\"},{\"type\":\"text\",\"text\":\"🔹 Пример: стопка тарелок — снимаешь сначала верхнюю.\"}]}]},{\"type\":\"listItem\",\"content\":[{\"type\":\"paragraph\",\"attrs\":{\"textAlign\":null},\"content\":[{\"type\":\"text\",\"marks\":[{\"type\":\"bold\"}],\"text\":\"Очередь\"},{\"type\":\"text\",\"text\":\" — принцип \"},{\"type\":\"text\",\"marks\":[{\"type\":\"bold\"}],\"text\":\"FIFO (First In, First Out)\"},{\"type\":\"text\",\"text\":\": первым добавил — первым достал.\"},{\"type\":\"hardBreak\"},{\"type\":\"text\",\"text\":\"🔹 Пример: очередь в магазине — кто пришёл раньше, тот уйдёт раньше.\"}]}]}]},{\"type\":\"paragraph\",\"attrs\":{\"textAlign\":null},\"content\":[{\"type\":\"text\",\"text\":\"Технически:\"}]},{\"type\":\"bulletList\",\"content\":[{\"type\":\"listItem\",\"content\":[{\"type\":\"paragraph\",\"attrs\":{\"textAlign\":null},\"content\":[{\"type\":\"text\",\"text\":\"В \"},{\"type\":\"text\",\"marks\":[{\"type\":\"bold\"}],\"text\":\"стеке\"},{\"type\":\"text\",\"text\":\" добавление и удаление происходят \"},{\"type\":\"text\",\"marks\":[{\"type\":\"bold\"}],\"text\":\"с одного конца\"},{\"type\":\"text\",\"text\":\" (вершины).\"}]}]},{\"type\":\"listItem\",\"content\":[{\"type\":\"paragraph\",\"attrs\":{\"textAlign\":null},\"content\":[{\"type\":\"text\",\"text\":\"В \"},{\"type\":\"text\",\"marks\":[{\"type\":\"bold\"}],\"text\":\"очереди\"},{\"type\":\"text\",\"text\":\" — \"},{\"type\":\"text\",\"marks\":[{\"type\":\"bold\"}],\"text\":\"добавление с хвоста\"},{\"type\":\"text\",\"text\":\", \"},{\"type\":\"text\",\"marks\":[{\"type\":\"bold\"}],\"text\":\"удаление с головы\"},{\"type\":\"text\",\"text\":\".\"}]}]}]},{\"type\":\"paragraph\",\"attrs\":{\"textAlign\":null},\"content\":[{\"type\":\"text\",\"text\":\"👉 Итог: стек хранит порядок «назад», очередь — «вперёд».\"}]}]}",
        "grade": "trainee",
        "language": null,
        "generationSource": "USER",
        "framework": null,
        "expectedAnswer": null,
        "categoryId": 136,
        "createdAt": "2025-10-21T08:17:34.837Z",
        "updatedAt": "2025-11-10T13:12:28.509Z",
        "favoriteByUsers": [],
        "userProgress": [],
        "category": {
          "id": 136,
          "title": "Очередь и Дек (Queue)",
          "directions": [
            {
              "categoryId": 136,
              "directionId": 3,
              "direction": {
                "id": 3,
                "title": "Computer science",
                "order": 3,
                "isReady": true,
                "isVisible": true,
                "languages": [],
                "hasGrades": null,
                "frameworks": [],
                "createdAt": "2025-09-07T10:01:17.530Z",
                "updatedAt": "2025-11-26T11:08:54.386Z"
              }
            }
          ],
          "parent": {
            "title": "Структуры данных",
            "id": 11,
            "parent": null
          }
        }
      },
      "previous": {
        "title": "Что означает “FIFO”?",
        "id": 1552,
        "premium": true,
        "category": {
          "id": 136,
          "parent": {
            "title": "Структуры данных",
            "id": 11,
            "parent": null
          },
          "directions": [
            {
              "directionId": 3
            }
          ]
        }
      },
      "next": {
        "title": "Какова временная сложность вставки в очередь?",
        "id": 1554,
        "premium": false,
        "category": {
          "id": 136,
          "parent": {
            "title": "Структуры данных",
            "id": 11,
            "parent": null
          },
          "directions": [
            {
              "directionId": 3
            }
          ]
        }
      }
    },
    {
      "current": {
        "id": 1554,
        "type": "boolean",
        "text": "{\"type\":\"doc\",\"content\":[{\"type\":\"paragraph\",\"attrs\":{\"textAlign\":null},\"content\":[{\"type\":\"text\",\"text\":\"Какова временная сложность вставки в очередь?\"}]}]}",
        "title": "Какова временная сложность вставки в очередь?",
        "order": 410504,
        "premium": false,
        "isPopular": false,
        "explanation": "{\"type\":\"doc\",\"content\":[{\"type\":\"paragraph\",\"attrs\":{\"textAlign\":null},\"content\":[{\"type\":\"text\",\"text\":\"Временная сложность операции \"},{\"type\":\"text\",\"marks\":[{\"type\":\"bold\"}],\"text\":\"вставки в очередь (enqueue)\"},{\"type\":\"text\",\"text\":\" обычно равна \"},{\"type\":\"text\",\"marks\":[{\"type\":\"bold\"}],\"text\":\"O(1)\"},{\"type\":\"text\",\"text\":\" — то есть выполняется за постоянное время.\"}]},{\"type\":\"paragraph\",\"attrs\":{\"textAlign\":null},\"content\":[{\"type\":\"text\",\"text\":\"Это потому, что элемент просто добавляется в конец очереди, без необходимости проходить весь список.\"}]},{\"type\":\"blockquote\",\"content\":[{\"type\":\"paragraph\",\"attrs\":{\"textAlign\":null},\"content\":[{\"type\":\"text\",\"text\":\"Исключение: если очередь реализована на основе массива с фиксированным размером и требуется его расширение — тогда в момент перераспределения памяти операция может занять \"},{\"type\":\"text\",\"marks\":[{\"type\":\"bold\"}],\"text\":\"O(n)\"},{\"type\":\"text\",\"text\":\", но это происходит редко (в амортизированном смысле сложность остаётся O(1)).\"}]}]},{\"type\":\"paragraph\",\"attrs\":{\"textAlign\":null}}]}",
        "grade": "trainee",
        "language": null,
        "generationSource": "USER",
        "framework": null,
        "expectedAnswer": null,
        "categoryId": 136,
        "createdAt": "2025-10-21T08:17:46.386Z",
        "updatedAt": "2025-10-21T08:17:46.386Z",
        "favoriteByUsers": [],
        "userProgress": [],
        "category": {
          "id": 136,
          "title": "Очередь и Дек (Queue)",
          "directions": [
            {
              "categoryId": 136,
              "directionId": 3,
              "direction": {
                "id": 3,
                "title": "Computer science",
                "order": 3,
                "isReady": true,
                "isVisible": true,
                "languages": [],
                "hasGrades": null,
                "frameworks": [],
                "createdAt": "2025-09-07T10:01:17.530Z",
                "updatedAt": "2025-11-26T11:08:54.386Z"
              }
            }
          ],
          "parent": {
            "title": "Структуры данных",
            "id": 11,
            "parent": null
          }
        }
      },
      "previous": {
        "title": "Чем очередь отличается от стека?",
        "id": 1553,
        "premium": true,
        "category": {
          "id": 136,
          "parent": {
            "title": "Структуры данных",
            "id": 11,
            "parent": null
          },
          "directions": [
            {
              "directionId": 3
            }
          ]
        }
      },
      "next": {
        "title": "Какова временная сложность удаления из очереди?",
        "id": 1555,
        "premium": false,
        "category": {
          "id": 136,
          "parent": {
            "title": "Структуры данных",
            "id": 11,
            "parent": null
          },
          "directions": [
            {
              "directionId": 3
            }
          ]
        }
      }
    },
    {
      "current": {
        "id": 1555,
        "type": "boolean",
        "text": "{\"type\":\"doc\",\"content\":[{\"type\":\"paragraph\",\"attrs\":{\"textAlign\":null},\"content\":[{\"type\":\"text\",\"text\":\"Какова временная сложность удаления из очереди?\"}]}]}",
        "title": "Какова временная сложность удаления из очереди?",
        "order": 410505,
        "premium": false,
        "isPopular": false,
        "explanation": "{\"type\":\"doc\",\"content\":[{\"type\":\"paragraph\",\"attrs\":{\"textAlign\":null},\"content\":[{\"type\":\"text\",\"text\":\"Временная сложность операции \"},{\"type\":\"text\",\"marks\":[{\"type\":\"bold\"}],\"text\":\"удаления из очереди (dequeue)\"},{\"type\":\"text\",\"text\":\" — \"},{\"type\":\"text\",\"marks\":[{\"type\":\"bold\"}],\"text\":\"O(1)\"},{\"type\":\"text\",\"text\":\".\"}]},{\"type\":\"paragraph\",\"attrs\":{\"textAlign\":null},\"content\":[{\"type\":\"text\",\"text\":\"Это потому, что элемент всегда удаляется \"},{\"type\":\"text\",\"marks\":[{\"type\":\"bold\"}],\"text\":\"с начала очереди\"},{\"type\":\"text\",\"text\":\", и для этого не нужно проходить весь список — достаточно просто сдвинуть указатель (или взять первый элемент, если очередь реализована на связном списке или кольцевом буфере).\"}]},{\"type\":\"blockquote\",\"content\":[{\"type\":\"paragraph\",\"attrs\":{\"textAlign\":null},\"content\":[{\"type\":\"text\",\"text\":\"Исключение — если очередь реализована на обычном массиве без кольцевой структуры и при удалении элементы физически сдвигаются, тогда сложность становится \"},{\"type\":\"text\",\"marks\":[{\"type\":\"bold\"}],\"text\":\"O(n)\"},{\"type\":\"text\",\"text\":\". Поэтому в практике используют кольцевые буферы или связные списки, чтобы сохранить \"},{\"type\":\"text\",\"marks\":[{\"type\":\"bold\"}],\"text\":\"O(1)\"},{\"type\":\"text\",\"text\":\".\"}]}]},{\"type\":\"paragraph\",\"attrs\":{\"textAlign\":null}}]}",
        "grade": "trainee",
        "language": null,
        "generationSource": "USER",
        "framework": null,
        "expectedAnswer": null,
        "categoryId": 136,
        "createdAt": "2025-10-21T08:17:59.273Z",
        "updatedAt": "2025-10-21T08:17:59.273Z",
        "favoriteByUsers": [],
        "userProgress": [],
        "category": {
          "id": 136,
          "title": "Очередь и Дек (Queue)",
          "directions": [
            {
              "categoryId": 136,
              "directionId": 3,
              "direction": {
                "id": 3,
                "title": "Computer science",
                "order": 3,
                "isReady": true,
                "isVisible": true,
                "languages": [],
                "hasGrades": null,
                "frameworks": [],
                "createdAt": "2025-09-07T10:01:17.530Z",
                "updatedAt": "2025-11-26T11:08:54.386Z"
              }
            }
          ],
          "parent": {
            "title": "Структуры данных",
            "id": 11,
            "parent": null
          }
        }
      },
      "previous": {
        "title": "Какова временная сложность вставки в очередь?",
        "id": 1554,
        "premium": false,
        "category": {
          "id": 136,
          "parent": {
            "title": "Структуры данных",
            "id": 11,
            "parent": null
          },
          "directions": [
            {
              "directionId": 3
            }
          ]
        }
      },
      "next": {
        "title": "Чем реализация очереди на списке отличается от реализации на массиве?",
        "id": 1556,
        "premium": false,
        "category": {
          "id": 136,
          "parent": {
            "title": "Структуры данных",
            "id": 11,
            "parent": null
          },
          "directions": [
            {
              "directionId": 3
            }
          ]
        }
      }
    },
    {
      "current": {
        "id": 1556,
        "type": "boolean",
        "text": "{\"type\":\"doc\",\"content\":[{\"type\":\"paragraph\",\"attrs\":{\"textAlign\":null},\"content\":[{\"type\":\"text\",\"text\":\"Чем реализация очереди на списке отличается от реализации на массиве?\"}]}]}",
        "title": "Чем реализация очереди на списке отличается от реализации на массиве?",
        "order": 410506,
        "premium": false,
        "isPopular": false,
        "explanation": "{\"type\":\"doc\",\"content\":[{\"type\":\"paragraph\",\"attrs\":{\"textAlign\":null},\"content\":[{\"type\":\"text\",\"text\":\"Различие между реализацией очереди на \"},{\"type\":\"text\",\"marks\":[{\"type\":\"bold\"}],\"text\":\"списке\"},{\"type\":\"text\",\"text\":\" и на \"},{\"type\":\"text\",\"marks\":[{\"type\":\"bold\"}],\"text\":\"массиве\"},{\"type\":\"text\",\"text\":\" — в способе хранения и управлении памятью:\"}]},{\"type\":\"orderedList\",\"attrs\":{\"start\":1,\"type\":null},\"content\":[{\"type\":\"listItem\",\"content\":[{\"type\":\"paragraph\",\"attrs\":{\"textAlign\":null},\"content\":[{\"type\":\"text\",\"marks\":[{\"type\":\"bold\"}],\"text\":\"Очередь на массиве\"}]},{\"type\":\"bulletList\",\"content\":[{\"type\":\"listItem\",\"content\":[{\"type\":\"paragraph\",\"attrs\":{\"textAlign\":null},\"content\":[{\"type\":\"text\",\"text\":\"Элементы хранятся в непрерывной области памяти.\"}]}]},{\"type\":\"listItem\",\"content\":[{\"type\":\"paragraph\",\"attrs\":{\"textAlign\":null},\"content\":[{\"type\":\"text\",\"text\":\"Индексы \"},{\"type\":\"text\",\"marks\":[{\"type\":\"code\"}],\"text\":\"head\"},{\"type\":\"text\",\"text\":\" и \"},{\"type\":\"text\",\"marks\":[{\"type\":\"code\"}],\"text\":\"tail\"},{\"type\":\"text\",\"text\":\" указывают на начало и конец очереди.\"}]}]},{\"type\":\"listItem\",\"content\":[{\"type\":\"paragraph\",\"attrs\":{\"textAlign\":null},\"content\":[{\"type\":\"text\",\"text\":\"При заполнении массива может потребоваться \"},{\"type\":\"text\",\"marks\":[{\"type\":\"bold\"}],\"text\":\"расширение\"},{\"type\":\"text\",\"text\":\" (копирование в новый массив).\"}]}]},{\"type\":\"listItem\",\"content\":[{\"type\":\"paragraph\",\"attrs\":{\"textAlign\":null},\"content\":[{\"type\":\"text\",\"text\":\"Если реализовать как \"},{\"type\":\"text\",\"marks\":[{\"type\":\"bold\"}],\"text\":\"кольцевой буфер\"},{\"type\":\"text\",\"text\":\", операции остаются O(1) без сдвигов.\"}]}]},{\"type\":\"listItem\",\"content\":[{\"type\":\"paragraph\",\"attrs\":{\"textAlign\":null},\"content\":[{\"type\":\"text\",\"text\":\"Минус — фиксированный размер (если не расширять).\"}]}]}]}]},{\"type\":\"listItem\",\"content\":[{\"type\":\"paragraph\",\"attrs\":{\"textAlign\":null},\"content\":[{\"type\":\"text\",\"marks\":[{\"type\":\"bold\"}],\"text\":\"Очередь на связном списке\"}]},{\"type\":\"bulletList\",\"content\":[{\"type\":\"listItem\",\"content\":[{\"type\":\"paragraph\",\"attrs\":{\"textAlign\":null},\"content\":[{\"type\":\"text\",\"text\":\"Каждый элемент хранит ссылку на следующий.\"}]}]},{\"type\":\"listItem\",\"content\":[{\"type\":\"paragraph\",\"attrs\":{\"textAlign\":null},\"content\":[{\"type\":\"text\",\"text\":\"Не требуется заранее задавать размер — очередь может расти динамически.\"}]}]},{\"type\":\"listItem\",\"content\":[{\"type\":\"paragraph\",\"attrs\":{\"textAlign\":null},\"content\":[{\"type\":\"text\",\"text\":\"Добавление в конец и удаление из начала происходят за \"},{\"type\":\"text\",\"marks\":[{\"type\":\"bold\"}],\"text\":\"O(1)\"},{\"type\":\"text\",\"text\":\".\"}]}]},{\"type\":\"listItem\",\"content\":[{\"type\":\"paragraph\",\"attrs\":{\"textAlign\":null},\"content\":[{\"type\":\"text\",\"text\":\"Минус — дополнительная память на хранение ссылок и менее компактное размещение данных.\"}]}]}]}]}]},{\"type\":\"paragraph\",\"attrs\":{\"textAlign\":null},\"content\":[{\"type\":\"text\",\"marks\":[{\"type\":\"bold\"}],\"text\":\"Вывод:\"},{\"type\":\"hardBreak\"},{\"type\":\"text\",\"text\":\"Массив — быстрее и компактнее, но ограничен размером.\"},{\"type\":\"hardBreak\"},{\"type\":\"text\",\"text\":\"Список — гибче, но требует больше памяти и чуть медленнее из-за работы с указателями.\"}]}]}",
        "grade": "trainee",
        "language": null,
        "generationSource": "USER",
        "framework": null,
        "expectedAnswer": null,
        "categoryId": 136,
        "createdAt": "2025-10-21T08:18:14.813Z",
        "updatedAt": "2025-10-21T08:18:14.813Z",
        "favoriteByUsers": [],
        "userProgress": [],
        "category": {
          "id": 136,
          "title": "Очередь и Дек (Queue)",
          "directions": [
            {
              "categoryId": 136,
              "directionId": 3,
              "direction": {
                "id": 3,
                "title": "Computer science",
                "order": 3,
                "isReady": true,
                "isVisible": true,
                "languages": [],
                "hasGrades": null,
                "frameworks": [],
                "createdAt": "2025-09-07T10:01:17.530Z",
                "updatedAt": "2025-11-26T11:08:54.386Z"
              }
            }
          ],
          "parent": {
            "title": "Структуры данных",
            "id": 11,
            "parent": null
          }
        }
      },
      "previous": {
        "title": "Какова временная сложность удаления из очереди?",
        "id": 1555,
        "premium": false,
        "category": {
          "id": 136,
          "parent": {
            "title": "Структуры данных",
            "id": 11,
            "parent": null
          },
          "directions": [
            {
              "directionId": 3
            }
          ]
        }
      },
      "next": {
        "title": "Что такое “сдвиг элементов” и почему это неэффективно?",
        "id": 1557,
        "premium": true,
        "category": {
          "id": 136,
          "parent": {
            "title": "Структуры данных",
            "id": 11,
            "parent": null
          },
          "directions": [
            {
              "directionId": 3
            }
          ]
        }
      }
    },
    {
      "current": {
        "id": 1557,
        "type": "boolean",
        "text": "{\"type\":\"doc\",\"content\":[{\"type\":\"paragraph\",\"attrs\":{\"textAlign\":null},\"content\":[{\"type\":\"text\",\"text\":\"Что такое “сдвиг элементов” и почему это неэффективно?\"}]}]}",
        "title": "Что такое “сдвиг элементов” и почему это неэффективно?",
        "order": 410507,
        "premium": true,
        "isPopular": false,
        "explanation": "{\"type\":\"doc\",\"content\":[{\"type\":\"paragraph\",\"attrs\":{\"textAlign\":null},\"content\":[{\"type\":\"text\",\"marks\":[{\"type\":\"bold\"}],\"text\":\"Сдвиг элементов\"},{\"type\":\"text\",\"text\":\" — это операция, при которой после удаления первого элемента массива все остальные \"},{\"type\":\"text\",\"marks\":[{\"type\":\"bold\"}],\"text\":\"перемещаются на одну позицию вперёд\"},{\"type\":\"text\",\"text\":\", чтобы заполнить освободившееся место.\"}]},{\"type\":\"paragraph\",\"attrs\":{\"textAlign\":null},\"content\":[{\"type\":\"text\",\"text\":\"Например, если была очередь \"},{\"type\":\"text\",\"marks\":[{\"type\":\"code\"}],\"text\":\"[A, B, C, D]\"},{\"type\":\"text\",\"text\":\",\"},{\"type\":\"hardBreak\"},{\"type\":\"text\",\"text\":\"и удалить \"},{\"type\":\"text\",\"marks\":[{\"type\":\"code\"}],\"text\":\"A\"},{\"type\":\"text\",\"text\":\", то массив станет \"},{\"type\":\"text\",\"marks\":[{\"type\":\"code\"}],\"text\":\"[B, C, D]\"},{\"type\":\"text\",\"text\":\" —\"},{\"type\":\"hardBreak\"},{\"type\":\"text\",\"text\":\"для этого нужно физически сдвинуть все элементы на одну позицию.\"}]},{\"type\":\"paragraph\",\"attrs\":{\"textAlign\":null},\"content\":[{\"type\":\"text\",\"text\":\"Почему это неэффективно:\"}]},{\"type\":\"bulletList\",\"content\":[{\"type\":\"listItem\",\"content\":[{\"type\":\"paragraph\",\"attrs\":{\"textAlign\":null},\"content\":[{\"type\":\"text\",\"text\":\"При каждом удалении приходится \"},{\"type\":\"text\",\"marks\":[{\"type\":\"bold\"}],\"text\":\"перемещать все оставшиеся элементы\"},{\"type\":\"text\",\"text\":\",\"}]}]},{\"type\":\"listItem\",\"content\":[{\"type\":\"paragraph\",\"attrs\":{\"textAlign\":null},\"content\":[{\"type\":\"text\",\"text\":\"Это занимает \"},{\"type\":\"text\",\"marks\":[{\"type\":\"bold\"}],\"text\":\"O(n)\"},{\"type\":\"text\",\"text\":\" времени, где \"},{\"type\":\"text\",\"marks\":[{\"type\":\"code\"}],\"text\":\"n\"},{\"type\":\"text\",\"text\":\" — количество элементов,\"}]}]},{\"type\":\"listItem\",\"content\":[{\"type\":\"paragraph\",\"attrs\":{\"textAlign\":null},\"content\":[{\"type\":\"text\",\"text\":\"При больших объёмах данных такие сдвиги резко замедляют программу.\"}]}]}]},{\"type\":\"paragraph\",\"attrs\":{\"textAlign\":null},\"content\":[{\"type\":\"text\",\"text\":\"Поэтому вместо обычного массива для очередей используют:\"}]},{\"type\":\"bulletList\",\"content\":[{\"type\":\"listItem\",\"content\":[{\"type\":\"paragraph\",\"attrs\":{\"textAlign\":null},\"content\":[{\"type\":\"text\",\"marks\":[{\"type\":\"bold\"}],\"text\":\"кольцевой буфер\"},{\"type\":\"text\",\"text\":\" (индексы циклично “оборачиваются”),\"}]}]},{\"type\":\"listItem\",\"content\":[{\"type\":\"paragraph\",\"attrs\":{\"textAlign\":null},\"content\":[{\"type\":\"text\",\"text\":\"или \"},{\"type\":\"text\",\"marks\":[{\"type\":\"bold\"}],\"text\":\"связный список\"},{\"type\":\"text\",\"text\":\", где удаление и добавление происходят за \"},{\"type\":\"text\",\"marks\":[{\"type\":\"bold\"}],\"text\":\"O(1)\"},{\"type\":\"text\",\"text\":\" без сдвига.\"}]}]}]},{\"type\":\"paragraph\",\"attrs\":{\"textAlign\":null}}]}",
        "grade": "trainee",
        "language": null,
        "generationSource": "USER",
        "framework": null,
        "expectedAnswer": null,
        "categoryId": 136,
        "createdAt": "2025-10-21T08:18:31.621Z",
        "updatedAt": "2025-11-10T13:12:31.420Z",
        "favoriteByUsers": [],
        "userProgress": [],
        "category": {
          "id": 136,
          "title": "Очередь и Дек (Queue)",
          "directions": [
            {
              "categoryId": 136,
              "directionId": 3,
              "direction": {
                "id": 3,
                "title": "Computer science",
                "order": 3,
                "isReady": true,
                "isVisible": true,
                "languages": [],
                "hasGrades": null,
                "frameworks": [],
                "createdAt": "2025-09-07T10:01:17.530Z",
                "updatedAt": "2025-11-26T11:08:54.386Z"
              }
            }
          ],
          "parent": {
            "title": "Структуры данных",
            "id": 11,
            "parent": null
          }
        }
      },
      "previous": {
        "title": "Чем реализация очереди на списке отличается от реализации на массиве?",
        "id": 1556,
        "premium": false,
        "category": {
          "id": 136,
          "parent": {
            "title": "Структуры данных",
            "id": 11,
            "parent": null
          },
          "directions": [
            {
              "directionId": 3
            }
          ]
        }
      },
      "next": {
        "title": "Что такое кольцевая очередь (circular queue)?",
        "id": 1558,
        "premium": false,
        "category": {
          "id": 136,
          "parent": {
            "title": "Структуры данных",
            "id": 11,
            "parent": null
          },
          "directions": [
            {
              "directionId": 3
            }
          ]
        }
      }
    },
    {
      "current": {
        "id": 1558,
        "type": "boolean",
        "text": "{\"type\":\"doc\",\"content\":[{\"type\":\"paragraph\",\"attrs\":{\"textAlign\":null},\"content\":[{\"type\":\"text\",\"text\":\"Что такое кольцевая очередь (circular queue)?\"}]}]}",
        "title": "Что такое кольцевая очередь (circular queue)?",
        "order": 410508,
        "premium": false,
        "isPopular": false,
        "explanation": "{\"type\":\"doc\",\"content\":[{\"type\":\"paragraph\",\"attrs\":{\"textAlign\":null},\"content\":[{\"type\":\"text\",\"marks\":[{\"type\":\"bold\"}],\"text\":\"Кольцевая очередь (circular queue)\"},{\"type\":\"text\",\"text\":\" — это вариант обычной очереди, реализованный на массиве, где \"},{\"type\":\"text\",\"marks\":[{\"type\":\"bold\"}],\"text\":\"конец логически соединён с началом\"},{\"type\":\"text\",\"text\":\", образуя «кольцо».\"}]},{\"type\":\"paragraph\",\"attrs\":{\"textAlign\":null},\"content\":[{\"type\":\"text\",\"text\":\"🔹 \"},{\"type\":\"text\",\"marks\":[{\"type\":\"bold\"}],\"text\":\"Идея:\"},{\"type\":\"hardBreak\"},{\"type\":\"text\",\"text\":\"Когда указатель конца (\"},{\"type\":\"text\",\"marks\":[{\"type\":\"code\"}],\"text\":\"rear\"},{\"type\":\"text\",\"text\":\") достигает последней ячейки массива, следующий элемент записывается \"},{\"type\":\"text\",\"marks\":[{\"type\":\"bold\"}],\"text\":\"в начало массива\"},{\"type\":\"text\",\"text\":\", если там есть свободное место.\"}]},{\"type\":\"paragraph\",\"attrs\":{\"textAlign\":null},\"content\":[{\"type\":\"text\",\"text\":\"🔹 \"},{\"type\":\"text\",\"marks\":[{\"type\":\"bold\"}],\"text\":\"Как работает:\"}]},{\"type\":\"bulletList\",\"content\":[{\"type\":\"listItem\",\"content\":[{\"type\":\"paragraph\",\"attrs\":{\"textAlign\":null},\"content\":[{\"type\":\"text\",\"text\":\"Добавление (enqueue) — элемент помещается в позицию \"},{\"type\":\"text\",\"marks\":[{\"type\":\"code\"}],\"text\":\"rear\"},{\"type\":\"text\",\"text\":\", затем \"},{\"type\":\"text\",\"marks\":[{\"type\":\"code\"}],\"text\":\"rear\"},{\"type\":\"text\",\"text\":\" сдвигается на 1 (по модулю длины массива).\"}]}]},{\"type\":\"listItem\",\"content\":[{\"type\":\"paragraph\",\"attrs\":{\"textAlign\":null},\"content\":[{\"type\":\"text\",\"text\":\"Удаление (dequeue) — элемент берётся из позиции \"},{\"type\":\"text\",\"marks\":[{\"type\":\"code\"}],\"text\":\"front\"},{\"type\":\"text\",\"text\":\", затем \"},{\"type\":\"text\",\"marks\":[{\"type\":\"code\"}],\"text\":\"front\"},{\"type\":\"text\",\"text\":\" сдвигается аналогично.\"}]}]},{\"type\":\"listItem\",\"content\":[{\"type\":\"paragraph\",\"attrs\":{\"textAlign\":null},\"content\":[{\"type\":\"text\",\"text\":\"Очередь считается \"},{\"type\":\"text\",\"marks\":[{\"type\":\"bold\"}],\"text\":\"пустой\"},{\"type\":\"text\",\"text\":\", если \"},{\"type\":\"text\",\"marks\":[{\"type\":\"code\"}],\"text\":\"front == rear\"},{\"type\":\"text\",\"text\":\",\"},{\"type\":\"hardBreak\"},{\"type\":\"text\",\"text\":\"и \"},{\"type\":\"text\",\"marks\":[{\"type\":\"bold\"}],\"text\":\"полной\"},{\"type\":\"text\",\"text\":\", если следующий за \"},{\"type\":\"text\",\"marks\":[{\"type\":\"code\"}],\"text\":\"rear\"},{\"type\":\"text\",\"text\":\" элемент равен \"},{\"type\":\"text\",\"marks\":[{\"type\":\"code\"}],\"text\":\"front\"},{\"type\":\"text\",\"text\":\".\"}]}]}]},{\"type\":\"paragraph\",\"attrs\":{\"textAlign\":null},\"content\":[{\"type\":\"text\",\"text\":\"🔹 \"},{\"type\":\"text\",\"marks\":[{\"type\":\"bold\"}],\"text\":\"Преимущество:\"},{\"type\":\"hardBreak\"},{\"type\":\"text\",\"text\":\"Нет нужды сдвигать элементы, как в обычном массиве.\"},{\"type\":\"hardBreak\"},{\"type\":\"text\",\"text\":\"Все операции — \"},{\"type\":\"text\",\"marks\":[{\"type\":\"bold\"}],\"text\":\"O(1)\"},{\"type\":\"text\",\"text\":\", и память используется эффективно.\"}]},{\"type\":\"paragraph\",\"attrs\":{\"textAlign\":null},\"content\":[{\"type\":\"text\",\"text\":\"Пример:\"}]},{\"type\":\"codeBlock\",\"attrs\":{\"language\":\"javascript\"},\"content\":[{\"type\":\"text\",\"text\":\"[ _, 10, 20, 30, _ ]\\n front→1      ↑rear\\n\"}]},{\"type\":\"paragraph\",\"attrs\":{\"textAlign\":null},\"content\":[{\"type\":\"text\",\"text\":\"После удаления \"},{\"type\":\"text\",\"marks\":[{\"type\":\"code\"}],\"text\":\"10\"},{\"type\":\"text\",\"text\":\" и добавления \"},{\"type\":\"text\",\"marks\":[{\"type\":\"code\"}],\"text\":\"40\"},{\"type\":\"text\",\"text\":\":\"}]},{\"type\":\"codeBlock\",\"attrs\":{\"language\":\"javascript\"},\"content\":[{\"type\":\"text\",\"text\":\"[ 40, _, 20, 30, _ ]\\n       ↑rear   front→2\\n\"}]},{\"type\":\"paragraph\",\"attrs\":{\"textAlign\":null}}]}",
        "grade": "trainee",
        "language": null,
        "generationSource": "USER",
        "framework": null,
        "expectedAnswer": null,
        "categoryId": 136,
        "createdAt": "2025-10-21T08:18:51.792Z",
        "updatedAt": "2025-10-21T08:18:51.792Z",
        "favoriteByUsers": [],
        "userProgress": [],
        "category": {
          "id": 136,
          "title": "Очередь и Дек (Queue)",
          "directions": [
            {
              "categoryId": 136,
              "directionId": 3,
              "direction": {
                "id": 3,
                "title": "Computer science",
                "order": 3,
                "isReady": true,
                "isVisible": true,
                "languages": [],
                "hasGrades": null,
                "frameworks": [],
                "createdAt": "2025-09-07T10:01:17.530Z",
                "updatedAt": "2025-11-26T11:08:54.386Z"
              }
            }
          ],
          "parent": {
            "title": "Структуры данных",
            "id": 11,
            "parent": null
          }
        }
      },
      "previous": {
        "title": "Что такое “сдвиг элементов” и почему это неэффективно?",
        "id": 1557,
        "premium": true,
        "category": {
          "id": 136,
          "parent": {
            "title": "Структуры данных",
            "id": 11,
            "parent": null
          },
          "directions": [
            {
              "directionId": 3
            }
          ]
        }
      },
      "next": {
        "title": "Что такое двусторонняя очередь (deque)?",
        "id": 1559,
        "premium": false,
        "category": {
          "id": 136,
          "parent": {
            "title": "Структуры данных",
            "id": 11,
            "parent": null
          },
          "directions": [
            {
              "directionId": 3
            }
          ]
        }
      }
    },
    {
      "current": {
        "id": 1559,
        "type": "boolean",
        "text": "{\"type\":\"doc\",\"content\":[{\"type\":\"paragraph\",\"attrs\":{\"textAlign\":null},\"content\":[{\"type\":\"text\",\"text\":\"Что такое двусторонняя очередь (deque)?\"}]}]}",
        "title": "Что такое двусторонняя очередь (deque)?",
        "order": 410509,
        "premium": false,
        "isPopular": false,
        "explanation": "{\"type\":\"doc\",\"content\":[{\"type\":\"paragraph\",\"attrs\":{\"textAlign\":null},\"content\":[{\"type\":\"text\",\"marks\":[{\"type\":\"bold\"}],\"text\":\"Двусторонняя очередь (deque, от “double-ended queue”)\"},{\"type\":\"text\",\"text\":\" — это структура данных, в которой элементы можно \"},{\"type\":\"text\",\"marks\":[{\"type\":\"bold\"}],\"text\":\"добавлять и удалять с обеих сторон\"},{\"type\":\"text\",\"text\":\" — и с начала, и с конца.\"}]},{\"type\":\"paragraph\",\"attrs\":{\"textAlign\":null},\"content\":[{\"type\":\"text\",\"text\":\"🔹 \"},{\"type\":\"text\",\"marks\":[{\"type\":\"bold\"}],\"text\":\"Основные операции:\"}]},{\"type\":\"bulletList\",\"content\":[{\"type\":\"listItem\",\"content\":[{\"type\":\"paragraph\",\"attrs\":{\"textAlign\":null},\"content\":[{\"type\":\"text\",\"marks\":[{\"type\":\"code\"}],\"text\":\"addFront(x)\"},{\"type\":\"text\",\"text\":\" — добавить элемент в начало,\"}]}]},{\"type\":\"listItem\",\"content\":[{\"type\":\"paragraph\",\"attrs\":{\"textAlign\":null},\"content\":[{\"type\":\"text\",\"marks\":[{\"type\":\"code\"}],\"text\":\"addRear(x)\"},{\"type\":\"text\",\"text\":\" — добавить элемент в конец,\"}]}]},{\"type\":\"listItem\",\"content\":[{\"type\":\"paragraph\",\"attrs\":{\"textAlign\":null},\"content\":[{\"type\":\"text\",\"marks\":[{\"type\":\"code\"}],\"text\":\"removeFront()\"},{\"type\":\"text\",\"text\":\" — удалить элемент из начала,\"}]}]},{\"type\":\"listItem\",\"content\":[{\"type\":\"paragraph\",\"attrs\":{\"textAlign\":null},\"content\":[{\"type\":\"text\",\"marks\":[{\"type\":\"code\"}],\"text\":\"removeRear()\"},{\"type\":\"text\",\"text\":\" — удалить элемент с конца,\"}]}]},{\"type\":\"listItem\",\"content\":[{\"type\":\"paragraph\",\"attrs\":{\"textAlign\":null},\"content\":[{\"type\":\"text\",\"marks\":[{\"type\":\"code\"}],\"text\":\"peekFront()\"},{\"type\":\"text\",\"text\":\" и \"},{\"type\":\"text\",\"marks\":[{\"type\":\"code\"}],\"text\":\"peekRear()\"},{\"type\":\"text\",\"text\":\" — посмотреть элементы без удаления.\"}]}]}]},{\"type\":\"paragraph\",\"attrs\":{\"textAlign\":null},\"content\":[{\"type\":\"text\",\"text\":\"🔹 \"},{\"type\":\"text\",\"marks\":[{\"type\":\"bold\"}],\"text\":\"Отличие от обычной очереди:\"},{\"type\":\"hardBreak\"},{\"type\":\"text\",\"text\":\"В обычной очереди добавление — только с конца, удаление — только с начала.\"},{\"type\":\"hardBreak\"},{\"type\":\"text\",\"text\":\"В deque обе стороны равноправны.\"}]},{\"type\":\"paragraph\",\"attrs\":{\"textAlign\":null},\"content\":[{\"type\":\"text\",\"text\":\"🔹 \"},{\"type\":\"text\",\"marks\":[{\"type\":\"bold\"}],\"text\":\"Применение:\"}]},{\"type\":\"bulletList\",\"content\":[{\"type\":\"listItem\",\"content\":[{\"type\":\"paragraph\",\"attrs\":{\"textAlign\":null},\"content\":[{\"type\":\"text\",\"text\":\"реализация \"},{\"type\":\"text\",\"marks\":[{\"type\":\"bold\"}],\"text\":\"стека и очереди\"},{\"type\":\"text\",\"text\":\" в одном объекте,\"}]}]},{\"type\":\"listItem\",\"content\":[{\"type\":\"paragraph\",\"attrs\":{\"textAlign\":null},\"content\":[{\"type\":\"text\",\"text\":\"задачи с “окнами” (например, максимум в скользящем окне),\"}]}]},{\"type\":\"listItem\",\"content\":[{\"type\":\"paragraph\",\"attrs\":{\"textAlign\":null},\"content\":[{\"type\":\"text\",\"text\":\"кэширование (LRU-алгоритмы),\"}]}]},{\"type\":\"listItem\",\"content\":[{\"type\":\"paragraph\",\"attrs\":{\"textAlign\":null},\"content\":[{\"type\":\"text\",\"text\":\"симметричная обработка данных, где нужно быстро работать с обоими концами.\"}]}]}]},{\"type\":\"paragraph\",\"attrs\":{\"textAlign\":null},\"content\":[{\"type\":\"text\",\"text\":\"Все основные операции deque выполняются за \"},{\"type\":\"text\",\"marks\":[{\"type\":\"bold\"}],\"text\":\"O(1)\"},{\"type\":\"text\",\"text\":\".\"}]}]}",
        "grade": "trainee",
        "language": null,
        "generationSource": "USER",
        "framework": null,
        "expectedAnswer": null,
        "categoryId": 136,
        "createdAt": "2025-10-21T08:19:09.920Z",
        "updatedAt": "2025-10-21T08:19:09.920Z",
        "favoriteByUsers": [],
        "userProgress": [],
        "category": {
          "id": 136,
          "title": "Очередь и Дек (Queue)",
          "directions": [
            {
              "categoryId": 136,
              "directionId": 3,
              "direction": {
                "id": 3,
                "title": "Computer science",
                "order": 3,
                "isReady": true,
                "isVisible": true,
                "languages": [],
                "hasGrades": null,
                "frameworks": [],
                "createdAt": "2025-09-07T10:01:17.530Z",
                "updatedAt": "2025-11-26T11:08:54.386Z"
              }
            }
          ],
          "parent": {
            "title": "Структуры данных",
            "id": 11,
            "parent": null
          }
        }
      },
      "previous": {
        "title": "Что такое кольцевая очередь (circular queue)?",
        "id": 1558,
        "premium": false,
        "category": {
          "id": 136,
          "parent": {
            "title": "Структуры данных",
            "id": 11,
            "parent": null
          },
          "directions": [
            {
              "directionId": 3
            }
          ]
        }
      },
      "next": {
        "title": "Какие операции поддерживает deque?",
        "id": 1560,
        "premium": false,
        "category": {
          "id": 136,
          "parent": {
            "title": "Структуры данных",
            "id": 11,
            "parent": null
          },
          "directions": [
            {
              "directionId": 3
            }
          ]
        }
      }
    },
    {
      "current": {
        "id": 1560,
        "type": "boolean",
        "text": "{\"type\":\"doc\",\"content\":[{\"type\":\"paragraph\",\"attrs\":{\"textAlign\":null},\"content\":[{\"type\":\"text\",\"text\":\"Какие операции поддерживает deque?\"}]}]}",
        "title": "Какие операции поддерживает deque?",
        "order": 410510,
        "premium": false,
        "isPopular": false,
        "explanation": "{\"type\":\"doc\",\"content\":[{\"type\":\"paragraph\",\"attrs\":{\"textAlign\":null},\"content\":[{\"type\":\"text\",\"marks\":[{\"type\":\"bold\"}],\"text\":\"Deque (двусторонняя очередь)\"},{\"type\":\"text\",\"text\":\" поддерживает следующие основные операции — все за \"},{\"type\":\"text\",\"marks\":[{\"type\":\"bold\"}],\"text\":\"O(1)\"},{\"type\":\"text\",\"text\":\":\"}]},{\"type\":\"orderedList\",\"attrs\":{\"start\":1,\"type\":null},\"content\":[{\"type\":\"listItem\",\"content\":[{\"type\":\"paragraph\",\"attrs\":{\"textAlign\":null},\"content\":[{\"type\":\"text\",\"marks\":[{\"type\":\"bold\"}],\"text\":\"addFront(x)\"},{\"type\":\"text\",\"text\":\" — добавить элемент \"},{\"type\":\"text\",\"marks\":[{\"type\":\"code\"}],\"text\":\"x\"},{\"type\":\"text\",\"text\":\" в начало.\"}]}]},{\"type\":\"listItem\",\"content\":[{\"type\":\"paragraph\",\"attrs\":{\"textAlign\":null},\"content\":[{\"type\":\"text\",\"marks\":[{\"type\":\"bold\"}],\"text\":\"addRear(x)\"},{\"type\":\"text\",\"text\":\" — добавить элемент \"},{\"type\":\"text\",\"marks\":[{\"type\":\"code\"}],\"text\":\"x\"},{\"type\":\"text\",\"text\":\" в конец.\"}]}]},{\"type\":\"listItem\",\"content\":[{\"type\":\"paragraph\",\"attrs\":{\"textAlign\":null},\"content\":[{\"type\":\"text\",\"marks\":[{\"type\":\"bold\"}],\"text\":\"removeFront()\"},{\"type\":\"text\",\"text\":\" — удалить и вернуть элемент из начала.\"}]}]},{\"type\":\"listItem\",\"content\":[{\"type\":\"paragraph\",\"attrs\":{\"textAlign\":null},\"content\":[{\"type\":\"text\",\"marks\":[{\"type\":\"bold\"}],\"text\":\"removeRear()\"},{\"type\":\"text\",\"text\":\" — удалить и вернуть элемент с конца.\"}]}]},{\"type\":\"listItem\",\"content\":[{\"type\":\"paragraph\",\"attrs\":{\"textAlign\":null},\"content\":[{\"type\":\"text\",\"marks\":[{\"type\":\"bold\"}],\"text\":\"peekFront()\"},{\"type\":\"text\",\"text\":\" — посмотреть первый элемент без удаления.\"}]}]},{\"type\":\"listItem\",\"content\":[{\"type\":\"paragraph\",\"attrs\":{\"textAlign\":null},\"content\":[{\"type\":\"text\",\"marks\":[{\"type\":\"bold\"}],\"text\":\"peekRear()\"},{\"type\":\"text\",\"text\":\" — посмотреть последний элемент без удаления.\"}]}]},{\"type\":\"listItem\",\"content\":[{\"type\":\"paragraph\",\"attrs\":{\"textAlign\":null},\"content\":[{\"type\":\"text\",\"marks\":[{\"type\":\"bold\"}],\"text\":\"isEmpty()\"},{\"type\":\"text\",\"text\":\" — проверить, пуста ли очередь.\"}]}]},{\"type\":\"listItem\",\"content\":[{\"type\":\"paragraph\",\"attrs\":{\"textAlign\":null},\"content\":[{\"type\":\"text\",\"marks\":[{\"type\":\"bold\"}],\"text\":\"size()\"},{\"type\":\"text\",\"text\":\" — вернуть количество элементов (иногда добавляется).\"}]}]}]},{\"type\":\"paragraph\",\"attrs\":{\"textAlign\":null},\"content\":[{\"type\":\"text\",\"text\":\"Благодаря доступу с обеих сторон deque можно использовать и как \"},{\"type\":\"text\",\"marks\":[{\"type\":\"bold\"}],\"text\":\"очередь (FIFO)\"},{\"type\":\"text\",\"text\":\", и как \"},{\"type\":\"text\",\"marks\":[{\"type\":\"bold\"}],\"text\":\"стек (LIFO)\"},{\"type\":\"text\",\"text\":\".\"}]}]}",
        "grade": "trainee",
        "language": null,
        "generationSource": "USER",
        "framework": null,
        "expectedAnswer": null,
        "categoryId": 136,
        "createdAt": "2025-10-21T08:19:22.779Z",
        "updatedAt": "2025-10-21T08:19:22.779Z",
        "favoriteByUsers": [],
        "userProgress": [],
        "category": {
          "id": 136,
          "title": "Очередь и Дек (Queue)",
          "directions": [
            {
              "categoryId": 136,
              "directionId": 3,
              "direction": {
                "id": 3,
                "title": "Computer science",
                "order": 3,
                "isReady": true,
                "isVisible": true,
                "languages": [],
                "hasGrades": null,
                "frameworks": [],
                "createdAt": "2025-09-07T10:01:17.530Z",
                "updatedAt": "2025-11-26T11:08:54.386Z"
              }
            }
          ],
          "parent": {
            "title": "Структуры данных",
            "id": 11,
            "parent": null
          }
        }
      },
      "previous": {
        "title": "Что такое двусторонняя очередь (deque)?",
        "id": 1559,
        "premium": false,
        "category": {
          "id": 136,
          "parent": {
            "title": "Структуры данных",
            "id": 11,
            "parent": null
          },
          "directions": [
            {
              "directionId": 3
            }
          ]
        }
      },
      "next": {
        "title": "Что такое очередь с приоритетом?",
        "id": 1561,
        "premium": true,
        "category": {
          "id": 136,
          "parent": {
            "title": "Структуры данных",
            "id": 11,
            "parent": null
          },
          "directions": [
            {
              "directionId": 3
            }
          ]
        }
      }
    },
    {
      "current": {
        "id": 1561,
        "type": "boolean",
        "text": "{\"type\":\"doc\",\"content\":[{\"type\":\"paragraph\",\"attrs\":{\"textAlign\":null},\"content\":[{\"type\":\"text\",\"text\":\"Что такое очередь с приоритетом?\"}]}]}",
        "title": "Что такое очередь с приоритетом?",
        "order": 410511,
        "premium": true,
        "isPopular": false,
        "explanation": "{\"type\":\"doc\",\"content\":[{\"type\":\"paragraph\",\"attrs\":{\"textAlign\":null},\"content\":[{\"type\":\"text\",\"marks\":[{\"type\":\"bold\"}],\"text\":\"Очередь с приоритетом (priority queue)\"},{\"type\":\"text\",\"text\":\" — это структура данных, где \"},{\"type\":\"text\",\"marks\":[{\"type\":\"bold\"}],\"text\":\"каждый элемент имеет приоритет\"},{\"type\":\"text\",\"text\":\", и при удалении выбирается \"},{\"type\":\"text\",\"marks\":[{\"type\":\"bold\"}],\"text\":\"не первый добавленный\"},{\"type\":\"text\",\"text\":\", а \"},{\"type\":\"text\",\"marks\":[{\"type\":\"bold\"}],\"text\":\"наиболее приоритетный\"},{\"type\":\"text\",\"text\":\" элемент.\"}]},{\"type\":\"paragraph\",\"attrs\":{\"textAlign\":null},\"content\":[{\"type\":\"text\",\"text\":\"🔹 \"},{\"type\":\"text\",\"marks\":[{\"type\":\"bold\"}],\"text\":\"Как это работает:\"}]},{\"type\":\"bulletList\",\"content\":[{\"type\":\"listItem\",\"content\":[{\"type\":\"paragraph\",\"attrs\":{\"textAlign\":null},\"content\":[{\"type\":\"text\",\"text\":\"Каждый элемент хранится как пара: \"},{\"type\":\"text\",\"marks\":[{\"type\":\"italic\"}],\"text\":\"(значение, приоритет)\"},{\"type\":\"text\",\"text\":\".\"}]}]},{\"type\":\"listItem\",\"content\":[{\"type\":\"paragraph\",\"attrs\":{\"textAlign\":null},\"content\":[{\"type\":\"text\",\"text\":\"При добавлении элемент помещается в очередь.\"}]}]},{\"type\":\"listItem\",\"content\":[{\"type\":\"paragraph\",\"attrs\":{\"textAlign\":null},\"content\":[{\"type\":\"text\",\"text\":\"При удалении (\"},{\"type\":\"text\",\"marks\":[{\"type\":\"code\"}],\"text\":\"dequeue\"},{\"type\":\"text\",\"text\":\") извлекается \"},{\"type\":\"text\",\"marks\":[{\"type\":\"bold\"}],\"text\":\"элемент с наивысшим приоритетом\"},{\"type\":\"text\",\"text\":\", а не тот, что был добавлен раньше.\"}]}]}]},{\"type\":\"paragraph\",\"attrs\":{\"textAlign\":null},\"content\":[{\"type\":\"text\",\"text\":\"🔹 \"},{\"type\":\"text\",\"marks\":[{\"type\":\"bold\"}],\"text\":\"Пример:\"},{\"type\":\"hardBreak\"},{\"type\":\"text\",\"text\":\"В больнице пациенты приходят в порядке очереди, но врач принимает сначала тех, у кого состояние тяжелее — приоритет выше.\"}]},{\"type\":\"paragraph\",\"attrs\":{\"textAlign\":null},\"content\":[{\"type\":\"text\",\"text\":\"🔹 \"},{\"type\":\"text\",\"marks\":[{\"type\":\"bold\"}],\"text\":\"Реализация:\"}]},{\"type\":\"bulletList\",\"content\":[{\"type\":\"listItem\",\"content\":[{\"type\":\"paragraph\",\"attrs\":{\"textAlign\":null},\"content\":[{\"type\":\"text\",\"text\":\"Самая частая — через \"},{\"type\":\"text\",\"marks\":[{\"type\":\"bold\"}],\"text\":\"кучу (heap)\"},{\"type\":\"text\",\"text\":\", обычно \"},{\"type\":\"text\",\"marks\":[{\"type\":\"bold\"}],\"text\":\"минимальную\"},{\"type\":\"text\",\"text\":\" или \"},{\"type\":\"text\",\"marks\":[{\"type\":\"bold\"}],\"text\":\"максимальную\"},{\"type\":\"text\",\"text\":\".\"}]},{\"type\":\"bulletList\",\"content\":[{\"type\":\"listItem\",\"content\":[{\"type\":\"paragraph\",\"attrs\":{\"textAlign\":null},\"content\":[{\"type\":\"text\",\"text\":\"Добавление (\"},{\"type\":\"text\",\"marks\":[{\"type\":\"code\"}],\"text\":\"insert\"},{\"type\":\"text\",\"text\":\") — \"},{\"type\":\"text\",\"marks\":[{\"type\":\"bold\"}],\"text\":\"O(log n)\"},{\"type\":\"text\",\"text\":\",\"}]}]},{\"type\":\"listItem\",\"content\":[{\"type\":\"paragraph\",\"attrs\":{\"textAlign\":null},\"content\":[{\"type\":\"text\",\"text\":\"Извлечение элемента с наивысшим приоритетом — \"},{\"type\":\"text\",\"marks\":[{\"type\":\"bold\"}],\"text\":\"O(log n)\"},{\"type\":\"text\",\"text\":\",\"}]}]},{\"type\":\"listItem\",\"content\":[{\"type\":\"paragraph\",\"attrs\":{\"textAlign\":null},\"content\":[{\"type\":\"text\",\"text\":\"Получение максимума/минимума без удаления — \"},{\"type\":\"text\",\"marks\":[{\"type\":\"bold\"}],\"text\":\"O(1)\"},{\"type\":\"text\",\"text\":\".\"}]}]}]}]}]},{\"type\":\"paragraph\",\"attrs\":{\"textAlign\":null},\"content\":[{\"type\":\"text\",\"text\":\"Таким образом, очередь с приоритетом — это \"},{\"type\":\"text\",\"marks\":[{\"type\":\"bold\"}],\"text\":\"очередь, где порядок определяется не временем поступления, а значением приоритета\"},{\"type\":\"text\",\"text\":\".\"}]}]}",
        "grade": "trainee",
        "language": null,
        "generationSource": "USER",
        "framework": null,
        "expectedAnswer": null,
        "categoryId": 136,
        "createdAt": "2025-10-21T08:19:41.571Z",
        "updatedAt": "2025-11-10T13:12:35.627Z",
        "favoriteByUsers": [],
        "userProgress": [],
        "category": {
          "id": 136,
          "title": "Очередь и Дек (Queue)",
          "directions": [
            {
              "categoryId": 136,
              "directionId": 3,
              "direction": {
                "id": 3,
                "title": "Computer science",
                "order": 3,
                "isReady": true,
                "isVisible": true,
                "languages": [],
                "hasGrades": null,
                "frameworks": [],
                "createdAt": "2025-09-07T10:01:17.530Z",
                "updatedAt": "2025-11-26T11:08:54.386Z"
              }
            }
          ],
          "parent": {
            "title": "Структуры данных",
            "id": 11,
            "parent": null
          }
        }
      },
      "previous": {
        "title": "Какие операции поддерживает deque?",
        "id": 1560,
        "premium": false,
        "category": {
          "id": 136,
          "parent": {
            "title": "Структуры данных",
            "id": 11,
            "parent": null
          },
          "directions": [
            {
              "directionId": 3
            }
          ]
        }
      },
      "next": {
        "title": "Как очередь используется в BFS (поиск в ширину)?",
        "id": 1562,
        "premium": false,
        "category": {
          "id": 136,
          "parent": {
            "title": "Структуры данных",
            "id": 11,
            "parent": null
          },
          "directions": [
            {
              "directionId": 3
            }
          ]
        }
      }
    },
    {
      "current": {
        "id": 1562,
        "type": "boolean",
        "text": "{\"type\":\"doc\",\"content\":[{\"type\":\"paragraph\",\"attrs\":{\"textAlign\":null},\"content\":[{\"type\":\"text\",\"text\":\"Как очередь используется в BFS (поиск в ширину)?\"}]}]}",
        "title": "Как очередь используется в BFS (поиск в ширину)?",
        "order": 410512,
        "premium": false,
        "isPopular": false,
        "explanation": "{\"type\":\"doc\",\"content\":[{\"type\":\"paragraph\",\"attrs\":{\"textAlign\":null},\"content\":[{\"type\":\"text\",\"text\":\"В алгоритме \"},{\"type\":\"text\",\"marks\":[{\"type\":\"bold\"}],\"text\":\"BFS (Breadth-First Search, поиск в ширину)\"},{\"type\":\"text\",\"text\":\" очередь используется для хранения вершин, которые нужно посетить \"},{\"type\":\"text\",\"marks\":[{\"type\":\"bold\"}],\"text\":\"в порядке их открытия\"},{\"type\":\"text\",\"text\":\".\"}]},{\"type\":\"paragraph\",\"attrs\":{\"textAlign\":null},\"content\":[{\"type\":\"text\",\"text\":\"🔹 \"},{\"type\":\"text\",\"marks\":[{\"type\":\"bold\"}],\"text\":\"Суть BFS:\"},{\"type\":\"hardBreak\"},{\"type\":\"text\",\"text\":\"Алгоритм обходит граф слоями — сначала все вершины, находящиеся на расстоянии 1 от начальной, затем на расстоянии 2, и так далее.\"}]},{\"type\":\"paragraph\",\"attrs\":{\"textAlign\":null},\"content\":[{\"type\":\"text\",\"text\":\"🔹 \"},{\"type\":\"text\",\"marks\":[{\"type\":\"bold\"}],\"text\":\"Роль очереди:\"}]},{\"type\":\"orderedList\",\"attrs\":{\"start\":1,\"type\":null},\"content\":[{\"type\":\"listItem\",\"content\":[{\"type\":\"paragraph\",\"attrs\":{\"textAlign\":null},\"content\":[{\"type\":\"text\",\"text\":\"В начале в очередь помещается \"},{\"type\":\"text\",\"marks\":[{\"type\":\"bold\"}],\"text\":\"стартовая вершина\"},{\"type\":\"text\",\"text\":\".\"}]}]},{\"type\":\"listItem\",\"content\":[{\"type\":\"paragraph\",\"attrs\":{\"textAlign\":null},\"content\":[{\"type\":\"text\",\"text\":\"Пока очередь не пуста:\"}]},{\"type\":\"bulletList\",\"content\":[{\"type\":\"listItem\",\"content\":[{\"type\":\"paragraph\",\"attrs\":{\"textAlign\":null},\"content\":[{\"type\":\"text\",\"text\":\"извлекается вершина из начала очереди (\"},{\"type\":\"text\",\"marks\":[{\"type\":\"code\"}],\"text\":\"dequeue\"},{\"type\":\"text\",\"text\":\"),\"}]}]},{\"type\":\"listItem\",\"content\":[{\"type\":\"paragraph\",\"attrs\":{\"textAlign\":null},\"content\":[{\"type\":\"text\",\"text\":\"все её \"},{\"type\":\"text\",\"marks\":[{\"type\":\"bold\"}],\"text\":\"непосещённые соседи добавляются в конец\"},{\"type\":\"text\",\"text\":\" очереди (\"},{\"type\":\"text\",\"marks\":[{\"type\":\"code\"}],\"text\":\"enqueue\"},{\"type\":\"text\",\"text\":\").\"}]}]}]}]},{\"type\":\"listItem\",\"content\":[{\"type\":\"paragraph\",\"attrs\":{\"textAlign\":null},\"content\":[{\"type\":\"text\",\"text\":\"Этот процесс продолжается, пока все достижимые вершины не будут обработаны.\"}]}]}]},{\"type\":\"paragraph\",\"attrs\":{\"textAlign\":null},\"content\":[{\"type\":\"text\",\"text\":\"🔹 \"},{\"type\":\"text\",\"marks\":[{\"type\":\"bold\"}],\"text\":\"Почему именно очередь:\"},{\"type\":\"hardBreak\"},{\"type\":\"text\",\"text\":\"Очередь гарантирует порядок \"},{\"type\":\"text\",\"marks\":[{\"type\":\"bold\"}],\"text\":\"FIFO\"},{\"type\":\"text\",\"text\":\" —\"},{\"type\":\"hardBreak\"},{\"type\":\"text\",\"text\":\"все вершины одного уровня обрабатываются раньше, чем вершины следующего.\"}]},{\"type\":\"paragraph\",\"attrs\":{\"textAlign\":null},\"content\":[{\"type\":\"text\",\"text\":\"Именно поэтому BFS проходит граф \"},{\"type\":\"text\",\"marks\":[{\"type\":\"bold\"}],\"text\":\"по слоям\"},{\"type\":\"text\",\"text\":\", в отличие от DFS, который использует стек и идёт в глубину.\"}]}]}",
        "grade": "trainee",
        "language": null,
        "generationSource": "USER",
        "framework": null,
        "expectedAnswer": null,
        "categoryId": 136,
        "createdAt": "2025-10-21T08:20:03.255Z",
        "updatedAt": "2025-10-21T08:20:03.255Z",
        "favoriteByUsers": [],
        "userProgress": [],
        "category": {
          "id": 136,
          "title": "Очередь и Дек (Queue)",
          "directions": [
            {
              "categoryId": 136,
              "directionId": 3,
              "direction": {
                "id": 3,
                "title": "Computer science",
                "order": 3,
                "isReady": true,
                "isVisible": true,
                "languages": [],
                "hasGrades": null,
                "frameworks": [],
                "createdAt": "2025-09-07T10:01:17.530Z",
                "updatedAt": "2025-11-26T11:08:54.386Z"
              }
            }
          ],
          "parent": {
            "title": "Структуры данных",
            "id": 11,
            "parent": null
          }
        }
      },
      "previous": {
        "title": "Что такое очередь с приоритетом?",
        "id": 1561,
        "premium": true,
        "category": {
          "id": 136,
          "parent": {
            "title": "Структуры данных",
            "id": 11,
            "parent": null
          },
          "directions": [
            {
              "directionId": 3
            }
          ]
        }
      },
      "next": {
        "title": "В каких задачах часто используется очередь для решения?",
        "id": 1563,
        "premium": false,
        "category": {
          "id": 136,
          "parent": {
            "title": "Структуры данных",
            "id": 11,
            "parent": null
          },
          "directions": [
            {
              "directionId": 3
            }
          ]
        }
      }
    },
    {
      "current": {
        "id": 1563,
        "type": "boolean",
        "text": "{\"type\":\"doc\",\"content\":[{\"type\":\"paragraph\",\"attrs\":{\"textAlign\":null},\"content\":[{\"type\":\"text\",\"text\":\"В каких задачах часто используется очередь для решения?\"}]}]}",
        "title": "В каких задачах часто используется очередь для решения?",
        "order": 410513,
        "premium": false,
        "isPopular": false,
        "explanation": "{\"type\":\"doc\",\"content\":[{\"type\":\"paragraph\",\"attrs\":{\"textAlign\":null},\"content\":[{\"type\":\"text\",\"text\":\"Очередь используется там, где нужно \"},{\"type\":\"text\",\"marks\":[{\"type\":\"bold\"}],\"text\":\"обрабатывать элементы в порядке поступления\"},{\"type\":\"text\",\"text\":\" или \"},{\"type\":\"text\",\"marks\":[{\"type\":\"bold\"}],\"text\":\"по уровням\"},{\"type\":\"text\",\"text\":\", без возврата назад. Основные типичные задачи:\"}]},{\"type\":\"orderedList\",\"attrs\":{\"start\":1,\"type\":null},\"content\":[{\"type\":\"listItem\",\"content\":[{\"type\":\"paragraph\",\"attrs\":{\"textAlign\":null},\"content\":[{\"type\":\"text\",\"marks\":[{\"type\":\"bold\"}],\"text\":\"Обход графа в ширину (BFS)\"},{\"type\":\"text\",\"text\":\" — поиск кратчайшего пути, определение компонент связности, нахождение расстояний между вершинами.\"}]}]},{\"type\":\"listItem\",\"content\":[{\"type\":\"paragraph\",\"attrs\":{\"textAlign\":null},\"content\":[{\"type\":\"text\",\"marks\":[{\"type\":\"bold\"}],\"text\":\"Планирование задач (task scheduling)\"},{\"type\":\"text\",\"text\":\" — например, обработка процессов в ОС или заданий в принтере: кто первый поступил — тот первый выполняется.\"}]}]},{\"type\":\"listItem\",\"content\":[{\"type\":\"paragraph\",\"attrs\":{\"textAlign\":null},\"content\":[{\"type\":\"text\",\"marks\":[{\"type\":\"bold\"}],\"text\":\"Обработка потоков данных\"},{\"type\":\"text\",\"text\":\" — сетевые пакеты, сообщения в очередях RabbitMQ, Kafka и т. п.\"}]}]},{\"type\":\"listItem\",\"content\":[{\"type\":\"paragraph\",\"attrs\":{\"textAlign\":null},\"content\":[{\"type\":\"text\",\"marks\":[{\"type\":\"bold\"}],\"text\":\"Моделирование реальных очередей\"},{\"type\":\"text\",\"text\":\" — например, клиенты в банке, запросы на сервер.\"}]}]},{\"type\":\"listItem\",\"content\":[{\"type\":\"paragraph\",\"attrs\":{\"textAlign\":null},\"content\":[{\"type\":\"text\",\"marks\":[{\"type\":\"bold\"}],\"text\":\"Асинхронные операции и обработка событий\"},{\"type\":\"text\",\"text\":\" — очередь событий в браузерах или микросервисах.\"}]}]},{\"type\":\"listItem\",\"content\":[{\"type\":\"paragraph\",\"attrs\":{\"textAlign\":null},\"content\":[{\"type\":\"text\",\"marks\":[{\"type\":\"bold\"}],\"text\":\"Буферизация\"},{\"type\":\"text\",\"text\":\" — хранение данных, поступающих быстрее, чем их можно обработать (например, потоковое аудио или видео).\"}]}]}]},{\"type\":\"paragraph\",\"attrs\":{\"textAlign\":null},\"content\":[{\"type\":\"text\",\"text\":\"Во всех этих случаях важно, чтобы элементы \"},{\"type\":\"text\",\"marks\":[{\"type\":\"bold\"}],\"text\":\"обрабатывались строго в порядке поступления\"},{\"type\":\"text\",\"text\":\" — и это именно то, что обеспечивает очередь.\"}]}]}",
        "grade": "trainee",
        "language": null,
        "generationSource": "USER",
        "framework": null,
        "expectedAnswer": null,
        "categoryId": 136,
        "createdAt": "2025-10-21T08:20:18.667Z",
        "updatedAt": "2025-10-21T08:20:18.667Z",
        "favoriteByUsers": [],
        "userProgress": [],
        "category": {
          "id": 136,
          "title": "Очередь и Дек (Queue)",
          "directions": [
            {
              "categoryId": 136,
              "directionId": 3,
              "direction": {
                "id": 3,
                "title": "Computer science",
                "order": 3,
                "isReady": true,
                "isVisible": true,
                "languages": [],
                "hasGrades": null,
                "frameworks": [],
                "createdAt": "2025-09-07T10:01:17.530Z",
                "updatedAt": "2025-11-26T11:08:54.386Z"
              }
            }
          ],
          "parent": {
            "title": "Структуры данных",
            "id": 11,
            "parent": null
          }
        }
      },
      "previous": {
        "title": "Как очередь используется в BFS (поиск в ширину)?",
        "id": 1562,
        "premium": false,
        "category": {
          "id": 136,
          "parent": {
            "title": "Структуры данных",
            "id": 11,
            "parent": null
          },
          "directions": [
            {
              "directionId": 3
            }
          ]
        }
      },
      "next": {
        "title": "Что такое хеш-таблица?",
        "id": 1564,
        "premium": false,
        "category": {
          "id": 137,
          "parent": {
            "title": "Структуры данных",
            "id": 11,
            "parent": null
          },
          "directions": [
            {
              "directionId": 3
            }
          ]
        }
      }
    }
  ]
}